Workbook
Name Slicer_Bill_To: #N/A
Name Slicer_Description: #N/A

Sheet Summary
A1: Purchase
A2: Row Labels | B2: Sum of Ginger Kgs | C2: Sum of Garlic Kgs
A3: 45689 | B3: 130 | C3: 364
A4: 45717 | B4: 921 | C4: 1004
A5: 45748 | B5: 295 | C5: 419
A6: 45778 | B6: 593 | C6: 829
A7: 45809 | B7: 350 | C7: 1381
A8: 45839 | B8: 514.9 | C8: 329
A9: 45870 | B9: 575 | C9: 889
A10: 45901 | B10: 640 | C10: 1154
A11: Grand Total | B11: 4018.9 | C11: 6369
A23: Sales & Expences
A24: Row Labels | B24: Sum of Sales | C24: Sum of Expences
A25: 45689 | B25: 21450 | C25: 26975
A26: 45717 | B26: 188580 | C26: 162135
A27: 45748 | B27: 105060 | C27: 114833
A28: 45778 | B28: 133160 | C28: 154562
A29: 45809 | B29: 126385 | C29: 173669
A30: 45839 | B30: 164755 | C30: 89496
A31: 45870 | B31: 173370 | C31: 170293
A32: 45901 | B32: 229785 | C32: 173935
A33: Grand Total | B33: 1142545 | C33: 1065898

Sheet Raw Materials
A1: Raw Materials Procurement | B1: 2025
A2: Date | B2: Description | C2: Supplier | D2: Kgs | E2: Unit Price | F2: Transportation | G2: Price | H2: Remarks
A3: 45693 | B3: Garlic | D3: 62 | E3: 90 | G3: 5580 | H3: Rs90 per kg
A4: 45706 | B4: Ginger | D4: 40 | E4: 47.5 | F4: 200 | G4: 2100
A5: 45708 | B5: Garlic | D5: 76 | E5: 85 | F5: 560 | G5: 7020
A6: 45712 | B6: Garlic | D6: 66 | E6: 80 | F6: 520 | G6: 5800 | H6: Advance payment | K6: Date | L6: (All)
A7: 45712 | B7: Ginger | D7: 30 | G7: 1300
A8: 45714 | B8: Ginger | D8: 60 | E8: 40 | F8: 100 | G8: 2500
A9: 45716 | B9: Garlic | C9: PK Garlic Vadugapatti | D9: 160 | E9: 80 | F9: 1050 | G9: 13850 | K9: Description | L9: Sum of Kgs | M9: Sum of Price
A10: 45719 | B10: Ginger | C10: Local Purchase | D10: 20 | E10: 60 | G10: 1200 | K10: Garlic | L10: 6129 | M10: 501837.1
A11: 45720 | B11: Garlic | C11: PK Garlic Vadugapatti | D11: 98 | E11: 80 | F11: 685 | G11: 8525 | K11: Ginger | L11: 4024.9 | M11: 205884.87
A12: 45720 | B12: Ginger | C12: Bala Vegetables | D12: 56 | E12: 43 | F12: 100 | G12: 2500 | K12: Grand Total | L12: 10153.9 | M12: 707721.97
A13: 45723 | B13: Ginger | C13: Bala Vegetables | D13: 56 | E13: 43 | F13: 100 | G13: 2500
A14: 45724 | B14: Garlic | C14: PK Garlic Vadugapatti | D14: 137 | E14: 80 | F14: 810 | G14: 11770
A15: 45729 | B15: Ginger | C15: Bala Vegetables | D15: 56 | E15: 42.85 | F15: 100.4 | G15: 2500
A16: 45731 | B16: Garlic | C16: PK Garlic Vadugapatti | D16: 165 | E16: 80 | F16: 1010 | G16: 14210
A17: 45731 | B17: Ginger | C17: Jakakodi Traders | D17: 56 | E17: 38.39 | F17: 100.16 | G17: 2250 | K17: Count of Kgs | L17: Column Labels
A18: 45733 | B18: Ginger | C18: Jakakodi Traders | D18: 56 | E18: 38.39 | F18: 100.16 | G18: 2250 | K18: Row Labels | L18: Garlic | M18: Ginger | N18: Grand Total
A19: 45735 | B19: Ginger | C19: Jakakodi Traders | D19: 56 | E19: 38.39 | F19: 100.16 | G19: 2250 | K19: 45712 | L19: 1 | M19: 1 | N19: 2
A20: 45736 | B20: Ginger | C20: Jakakodi Traders | D20: 56 | E20: 38.39 | F20: 100.16 | G20: 2250 | K20: 45720 | L20: 1 | M20: 1 | N20: 2
A21: 45737 | B21: Ginger | C21: Jakakodi Traders | D21: 56 | E21: 38.39 | F21: 100.16 | G21: 2250 | K21: 45731 | L21: 1 | M21: 1 | N21: 2
A22: 45738 | B22: Ginger | C22: Ameen Bandary | D22: 5 | E22: 50 | G22: 250 | K22: 45738 | L22: 2 | M22: 1 | N22: 3
A23: 45738 | B23: Garlic | C23: Ameen Bandary | D23: 10 | E23: 75 | G23: 750 | K23: 45743 | L23: 2 | M23: 2 | N23: 4
A24: 45738 | B24: Garlic | C24: PK Garlic Vadugapatti | D24: 156 | E24: 80 | F24: 910 | G24: 13390 | K24: 45746 | L24: 1 | M24: 1 | N24: 2
A25: 45740 | B25: Ginger | C25: Jakakodi Traders | D25: 56 | E25: 38.39 | F25: 100.16 | G25: 2250 | K25: 45758 | L25: 1 | M25: 1 | N25: 2
A26: 45741 | B26: Ginger | C26: Jakakodi Traders | D26: 56 | E26: 38.39 | F26: 100.16 | G26: 2250 | K26: 45762 | L26: 2 | M26: 1 | N26: 3
A27: 45742 | B27: Ginger | C27: Jakakodi Traders | D27: 56 | E27: 38.39 | F27: 100.16 | G27: 2250 | K27: 45791 | L27: 2 | N27: 2
A28: 45743 | B28: Garlic | C28: PK Garlic Vadugapatti | D28: 160 | E28: 80 | F28: 570 | G28: =(D28*E28)+F28 -> 13370 | K28: 45807 | L28: 1 | M28: 2 | N28: 3
A29: 45743 | B29: Garlic | C29: PK Garlic Vadugapatti | D29: 120 | E29: 85 | F29: 1000 | G29: =(D29*E29)+F29 -> 11200 | K29: 45813 | L29: 2 | N29: 2
A30: 45743 | B30: Ginger | C30: Jakakodi Traders | D30: 56 | E30: 38.39 | F30: 100.16 | G30: 2250 | K30: 45830 | L30: 2 | N30: 2
A31: 45743 | B31: Ginger | C31: Jakakodi Traders | D31: 56 | E31: 38.39 | F31: 100.16 | G31: 2250 | K31: 45832 | L31: 1 | M31: 1 | N31: 2
A32: 45744 | B32: Ginger | C32: Jakakodi Traders | D32: 56 | E32: 38.39 | F32: 100.16 | G32: 2250 | K32: 45849 | L32: 1 | M32: 1 | N32: 2
A33: 45745 | B33: Ginger | C33: Jakakodi Traders | D33: 56 | E33: 38.39 | F33: 100.16 | G33: 2250 | K33: 45850 | L33: 1 | M33: 1 | N33: 2
A34: 45746 | B34: Ginger | C34: Jakakodi Traders | D34: 56 | E34: 38.39 | F34: 100.16 | G34: 2250 | K34: 45853 | L34: 1 | M34: 1 | N34: 2
A35: 45746 | B35: Garlic | C35: PK Garlic Vadugapatti | D35: 158 | E35: 80 | F35: 1020 | G35: =(D35*E35)+F35 -> 13660 | K35: 45857 | L35: 1 | M35: 1 | N35: 2
A36: 45751 | B36: Ginger | C36: Jakakodi Traders | D36: 56 | E36: 36.6 | F36: 100.4 | G36: =(D36*E36)+F36 -> 2150 | K36: 45859 | L36: 1 | M36: 1 | N36: 2
A37: 45758 | B37: Garlic | C37: Ameen Bandary | D37: 11 | E37: 80 | G37: =(D37*E37)+F37 -> 880 | K37: 45875 | L37: 1 | M37: 1 | N37: 2
A38: 45758 | B38: Ginger | C38: Ameen Bandary | D38: 15 | E38: 50 | G38: =(D38*E38)+F38 -> 750 | K38: 45877 | L38: 2 | M38: 1 | N38: 3
A39: 45759 | B39: Ginger | C39: Jakakodi Traders | D39: 56 | E39: 38.39 | F39: 100.16 | G39: 2250 | K39: 45891 | L39: 2 | N39: 2
A40: 45762 | B40: Garlic | C40: PK Garlic Vadugapatti | D40: 129 | E40: 70 | G40: =(D40*E40)+F40 -> 9030 | K40: 45900 | L40: 1 | M40: 1 | N40: 2
A41: 45762 | B41: Garlic | C41: PK Garlic Vadugapatti | D41: 87 | E41: 75 | F41: 1020 | G41: =(D41*E41)+F41 -> 7545 | K41: 45903 | L41: 1 | M41: 1 | N41: 2
A42: 45762 | B42: Ginger | C42: Jakakodi Traders | D42: 56 | E42: 36.6 | F42: 100.4 | G42: =(D42*E42)+F42 -> 2150 | K42: 45908 | L42: 2 | M42: 1 | N42: 3
A43: 45766 | B43: Ginger | C43: Jakakodi Traders | D43: 56 | E43: 36.6 | F43: 100.4 | G43: =(D43*E43)+F43 -> 2150 | K43: 45911 | L43: 2 | M43: 1 | N43: 3
A44: 45768 | B44: Garlic | C44: PK Garlic Vadugapatti | D44: 192 | E44: 75 | F44: 1000 | G44: =(D44*E44)+F44 -> 15400 | K44: 45930 | L44: 2 | N44: 2
A45: 45770 | B45: Ginger | C45: Jakakodi Traders | D45: 56 | E45: 36.6 | F45: 100.4 | G45: =(D45*E45)+F45 -> 2150 | K45: Grand Total | L45: 37 | M45: 23 | N45: 60
A46: 45773 | B46: Ginger | C46: Jakakodi Traders | D46: 56 | E46: 36.6 | F46: 100.4 | G46: =(D46*E46)+F46 -> 2150
A47: 45778 | B47: Ginger | C47: Jakakodi Traders | D47: 54 | E47: 33.33 | F47: 100.18 | G47: =(D47*E47)+F47 -> 1900
A48: 45779 | B48: Garlic | C48: PK Garlic Vadugapatti | D48: 220 | E48: 81.5 | F48: 0 | G48: =(D48*E48)+F48 -> 17930
A49: 45783 | B49: Ginger | C49: Jakakodi Traders | D49: 52 | E49: 33.65 | F49: 0.2 | G49: =(D49*E49)+F49 -> 1750
A50: 45787 | B50: Ginger | C50: Jakakodi Traders | D50: 54 | E50: 34.25 | F50: 0.5 | G50: =(D50*E50)+F50 -> 1850
A51: 45791 | B51: Garlic | C51: PK Garlic Vadugapatti | D51: 388 | E51: 70 | F51: 2900 | G51: =(D51*E51)+F51 -> 30060
A52: 45791 | B52: Garlic | C52: PK Garlic Vadugapatti | D52: 197 | E52: 65 | F52: 0 | G52: =(D52*E52)+F52 -> 12805
A53: 45792 | B53: Ginger | C53: Jakakodi Traders | D53: 50 | E53: 39 | F53: 0 | G53: =(D53*E53)+F53 -> 1950
A54: 45796 | B54: Ginger | C54: Mass Traders | D54: 250 | E54: 35 | F54: 0 | G54: =(D54*E54)+F54 -> 8750
A55: 45800 | B55: Garlic | C55: Nilaa Wholesale Supplies | D55: 20 | E55: 75 | F55: 0 | G55: =(D55*E55)+F55 -> 1500
A56: 45802 | B56: Ginger | C56: Jakakodi Traders | D56: 50 | E56: 43 | F56: 0 | G56: =(D56*E56)+F56 -> 2150
A57: 45804 | B57: Ginger | C57: Jakakodi Traders | D57: 50 | E57: 49 | F57: 0 | G57: =(D57*E57)+F57 -> 2450
... A83: 45857 | B83: Ginger | C83: Jakakodi Traders | D83: 50 | E83: 50 | F83: 0 | G83: =(D83*E83)+F83 -> 2500
A84: 45857 | B84: Garlic | C84: Nilaa Wholesale Supplies | D84: 10 | E84: 90 | F84: 0 | G84: =(D84*E84)+F84 -> 900 | K84: 2900 | L84: 3100
A85: 45859 | B85: Ginger | C85: Jakakodi Traders | D85: 50 | E85: 58 | F85: 0 | G85: =(D85*E85)+F85 -> 2900 | K85: 50 | L85: 54.2
A86: 45859 | B86: Garlic | C86: Nilaa Wholesale Supplies | D86: 10 | E86: 90 | F86: 0 | G86: =(D86*E86)+F86 -> 900 | K86: =K84/50 -> 58 | L86: =L84/L85 -> 57.195572
A87: 45861 | B87: Garlic | C87: Nilaa Wholesale Supplies | D87: 225 | E87: 95 | F87: 0 | G87: =(D87*E87)+F87 -> 21375
A88: 45862 | B88: Ginger | C88: Jakakodi Traders | D88: 50 | E88: 58 | F88: 100 | G88: =(D88*E88)+F88 -> 3000
A89: 45865 | B89: Ginger | C89: Jakakodi Traders | D89: 56.7 | E89: 54.6737 | F89: 100 | G89: =(D89*E89)+F89 -> 3199.9988
A90: 45867 | B90: Ginger | C90: Jakakodi Traders | D90: 54.2 | E90: 57.1955 | F90: 100 | G90: =(D90*E90)+F90 -> 3199.9961
A91: 45871 | B91: Ginger | C91: Jakakodi Traders | D91: 56 | E91: 69.65 | F91: 0 | G91: =(D91*E91)+F91 -> 3900.4
A92: 45875 | B92: Garlic | C92: Nilaa Wholesale Supplies | D92: 66 | E92: 95 | F92: 0 | G92: =(D92*E92)+F92 -> 6270
A93: 45875 | B93: Ginger | C93: Jakakodi Traders | D93: 56 | E93: 67.85 | F93: 0.4 | G93: =(D93*E93)+F93 -> 3800
A94: 45877 | B94: Ginger | C94: Jakakodi Traders | D94: 113 | E94: 67.26 | F94: -0.38 | G94: =(D94*E94)+F94 -> 7600
A95: 45877 | B95: Garlic | C95: Nilaa Wholesale Supplies | D95: 34 | E95: 95 | F95: 0 | G95: =(D95*E95)+F95 -> 3230
A96: 45877 | B96: Garlic | C96: Mass Traders | D96: 197 | E96: 65 | F96: 1050 | G96: =(D96*E96)+F96 -> 13855
A97: 45881 | B97: Ginger | C97: Jakakodi Traders | D97: 50 | E97: 80 | F97: 0 | G97: =(D97*E97)+F97 -> 4000
A98: 45884 | B98: Ginger | C98: Jakakodi Traders | D98: 50 | E98: 80 | F98: 0 | G98: =(D98*E98)+F98 -> 4000
... A121: 45919 | B121: Garlic | C121: SVG Garlics | D121: 171 | E121: 65 | F121: 1150 | G121: =(D121*E121)+F121 -> 12265
A122: 45925 | B122: Ginger | C122: Jakakodi Traders | D122: 50 | E122: 72 | G122: =(D122*E122)+F122 -> 3600
A123: 45929 | B123: Ginger | C123: Jakakodi Traders | D123: 50 | E123: 72 | G123: =(D123*E123)+F123 -> 3600
A124: 45930 | B124: Garlic | C124: SVG Garlics | D124: 80 | E124: 65 | F124: 1170 | G124: =(D124*E124)+F124 -> 6370
A125: 45930 | B125: Garlic | C125: SVG Garlics | D125: 160 | E125: 60 | F125: 0 | G125: =(D125*E125)+F125 -> 9600
B130: Total | D130: =SUM(D3:D121) -> 10153.9 | G130: =SUM(G3:G129) -> 730891.97
C135: Raw Material | D135: 1362
C136: Wastage | D136: 272.4 | E136: 20
C137: Total Production | D137: 1362 | E137: 1089.6
C139: Sales Projection avg 140/kg | D139: 190680
A143: Month | B143: Ginger Kgs | C143: Ginger cost | D143: Garlic Kgs | E143: Garlic cost | F143: Monthly RM purchase cost | L143: Row Labels | M143: Sum of Ginger Kgs | N143: Sum of Garlic Kgs | O143: Sum of Ginger cost | P143: Sum of Garlic cost
A144: 45689 | B144: 130 | C144: 5900 | D144: 364 | E144: 32250 | F144: =SUM(C144,E144) -> 38150 | L144: 45689 | M144: 130 | N144: 364 | O144: 5900 | P144: 32250
A145: 45717 | B145: 921 | C145: 38200 | D145: 1004 | E145: 86875 | F145: =SUM(C145,E145) -> 125075 | L145: 45717 | M145: 921 | N145: 1004 | O145: 38200 | P145: 86875
A146: 45748 | B146: 295 | C146: 13750 | D146: 419 | E146: 32855 | F146: =SUM(C146,E146) -> 46605 | L146: 45748 | M146: 295 | N146: 419 | O146: 13750 | P146: 32855
A147: 45778 | B147: 593 | C147: 22475 | D147: 829 | E147: 62595 | F147: =SUM(C147,E147) -> 85070 | L147: 45778 | M147: 593 | N147: 829 | O147: 22475 | P147: 62595
A148: 45809 | B148: 350 | C148: 16450 | D148: 1381 | E148: 111892 | F148: =SUM(C148,E148) -> 128342 | L148: 45809 | M148: 350 | N148: 1381 | O148: 16450 | P148: 111892
A149: 45839 | B149: 514.9 | C149: 25700 | D149: 329 | E149: 30735 | F149: =SUM(C149,E149) -> 56435 | L149: 45839 | M149: 514.9 | N149: 329 | O149: 25700 | P149: 30735
A150: 45870 | B150: 575 | C150: 42800 | D150: 889 | E150: 82205 | F150: =SUM(C150,E150) -> 125005 | L150: Grand Total | M150: 2803.9 | N150: 4326 | O150: 122475 | P150: 357202
A151: 45901 | B151: 640 | C151: 45609.48 | D151: 1154 | E151: 81350 | F151: =SUM(C151,E151) -> 126959.48
A152: 45931
A153: 45962
A154: 45992
A155: Total | B155: =SUBTOTAL(9,B144:B154) -> 4018.9 | C155: =SUBTOTAL(9,C144:C154) -> 210884.48 | D155: =SUBTOTAL(9,D144:D154) -> 6369 | E155: =SUBTOTAL(9,E144:E154) -> 520757 | F155: =SUBTOTAL(9,F144:F154) -> 731641.48

Sheet Feb 2025 - Sales
A1: Date | B1: Description | C1: Sales | D1: Expences | E1: Credit | F1: Remarks
B2: Petty Cash | C2: 42928 | F2: Hassan's Investment balance, Tobe returned. This includes Rs10550 of Garlic ruturned refund amount.
A3: 45708 | B3: KG ???? | C3: 4710
A4: 45709 | B4: 4 kg paste 2 kg peeled | C4: 1040
A5: 45710 | B5: Paste 1kg - 150 Peeled 2 kg - 230*2 = 460 Paste 130*6 = 780 Paste 130*7 = 910 | C5: 2300
A6: 45710 | B6: Tea & Cleaning Items | D6: 140
A7: 45710 | B7: Ansari sari sales balance - 770 | C7: 770
A8: 45711 | B8: 4 kg paste - 560 2 kg peeled - 480 | C8: 1040
A9: 45711 | B9: Expenses Water cane 3* 35 =105 Garlic parcel + auto fare - 520 | D9: 625
A10: 45712 | B10: Paste 2 kg - 280 (hasan) 8 kg - 1040 Peeled 2 kg - 460 Total 1780 | C10: 1780
A11: 45713 | B11: 1 kg - 150 1 kg - 130 Total - 280 only | C11: 280
A12: 45713 | B12: Tea | D12: 50
A13: 45714 | B13: Nagore dealer 19 kg *130 = 2470 Peeled 2 kg * 230 = 460 Total - 2930 | C13: 2930
A14: 45714 | B14: Tea - 50 | D14: 50
A15: 45714 | B15: Ginger 60 kg - 2400 | D15: 2400
A16: 45714 | B16: Delivery - 100 | D16: 100
A17: 45714 | B17: Head cap & cloves - 710 | D17: 710
A18: 45714 | B18: Property Rent - Jan 2025 | D18: 9000
A19: 45715 | B19: Nagore dealer 19 kg | C19: 1620 | E19: 1290 | F19: Credit to Riluwan
A20: 45715 | B20: Credit Riluwan Cleared | C20: 1290
A21: 45716 | B21: Garlic 160kg | D21: 13850
A22: 45716 | B22: 28/2/25 sales Counter sales - 150 1 kg Counter sales - 150 1 kg Counter sales - 130 500grm Rilwan ( buket )-120*6kg 720 (paste) - 130*16kg 2080 ( peeled) - 230* 2 kg 460 Total Sales - 3690 | C22: 3690
A23: 45716 | B23: Tea Exp | D23: 50
B24: Total Sales | C24: =SUM(C3:C23) -> 21450
B25: Total | C25: =SUM(C24,C2) -> 64378 | D25: =SUM(D3:D24) -> 26975
B28: Net Balance | C28: =C25-D25 -> 37403

Sheet Mar 2025 - Sales
A1: Date | B1: Invoice No | C1: Description | D1: Sales | E1: Expences | F1: Credit | G1: Remarks
A2: 45717 | C2: Opening Balance | D2: 37403
A3: 45717 | C3: Sales | D3: 7915
A4: 45717 | C4: Sales | D4: 1200
A5: 45717 | C5: Expenses | E5: 560 | G5: Pouch & Transport for Fridge
A6: 45718 | C6: Sales | D6: 7950 | J6: Row Labels | K6: Sum of Sales | L6: Sum of Expences
A7: 45718 | C7: Expenses | E7: 1110 | J7: Expenses | L7: 9940
A8: 45719 | C8: Sales | D8: 2260 | J8: Garlic Purchase | L8: 86875
A9: 45719 | C9: Ginger Purchase | E9: 1200 | G9: 20Kg * 60Rs | J9: Ginger Purchase | L9: 35950
A10: 45719 | C10: Expenses | E10: 575 | J10: Opening Balance | K10: 37403
A11: 45720 | C11: Garlic Purchase | E11: 8525 | G11: 98kg * 80Rs | J11: Petrol | L11: 600
A12: 45720 | B12: GST-023 | C12: Sales | D12: 4490 | J12: Rent | L12: 9000
A13: 45720 | C13: Expenses | E13: 100 | J13: Sales | K13: 188580
A14: 45720 | C14: Ginger Purchase | E14: 2500 | G14: 56kkgs * 43Rs | J14: Staff Salary | L14: 19220
A15: 45720 | C15: Expenses | E15: 800 | G15: 1Kg Box Purchase 100Nos | J15: Wifi Bill | L15: 550
A16: 45721 | B16: GST-023 | C16: Sales | D16: 1920 | J16: Grand Total | K16: 225983 | L16: 162135
A17: 45721 | B17: GST-024 | C17: Sales | D17: 720
A18: 45721 | C18: Expenses | E18: 140
A19: 45722 | B19: GST-025 | C19: Sales | D19: 5860
A20: 45722 | B20: GST-026 | C20: Sales | D20: 470
A21: 45722 | C21: Expenses | E21: 25
A22: 45723 | B22: GST-027 | C22: Sales | D22: 3150
A23: 45723 | C23: Ginger Purchase | E23: 2500 | G23: 56kg
A24: 45723 | C24: Expenses | E24: 1822 | G24: Thar Pai & Sealing machine
A25: 45723 | C25: Expenses | E25: 370 | G25: Tea, Petrol & Mask
A26: 45724 | C26: Garlic Purchase | E26: 11770 | G26: 137kg * 80 +810
A27: 45724 | B27: GST-028 | C27: Sales | D27: 5940
A28: 45724 | B28: GST-029 | C28: Sales | D28: 200
A29: 45724 | C29: Expenses | E29: 25
A30: 45725 | B30: GST-030 | C30: Sales | D30: 3000
A31: 45726 | B31: GST-031 | C31: Sales | D31: 6080
A32: 45726 | C32: Expenses | E32: 50
A33: 45727 | C33: Rent | E33: 9000
A34: 45727 | B34: GST-032 | C34: Sales | D34: 1080
A35: 45728 | B35: GST-033 | C35: Sales | D35: 2760
A36: 45728 | B36: GST-034 | C36: Sales | D36: 600
A37: 45728 | B37: GST-035 | C37: Sales | D37: 40
A38: 45728 | C38: Expenses | E38: 30
A39: 45729 | B39: GST-036 | C39: Sales | D39: 3730
A40: 45729 | C40: Ginger Purchase | E40: 2500 | G40: 56Kgs
A41: 45729 | C41: Expenses | E41: 1370 | G41: Essential items purchase
A42: 45729 | C42: Staff Salary | E42: 1000 | G42: Advance
A43: 45729 | C43: Expenses | E43: 213
A44: 45730 | B44: GST-037 | C44: Sales | D44: 3960
A45: 45730 | B45: GST-038 | C45: Sales | D45: 40
A46: 45730 | B46: GST-039 | C46: Sales | D46: 600
A47: 45730 | C47: Expenses | E47: 345
A48: 45731 | B48: GST-040 | C48: Sales | D48: 8645
A49: 45731 | C49: Garlic Purchase | E49: 14210 | G49: 165kg * 80Rs
A50: 45731 | C50: Ginger Purchase | E50: 2250 | G50: 56Kgs *38.39
A51: 45731 | C51: Expenses | E51: 50
A52: 45732 | B52: GST-041 | C52: Sales | D52: 1430
A53: 45732 | B53: GST-042 | C53: Sales | D53: 2705
A54: 45732 | B54: GST-043 | C54: Sales | D54: 120
A55: 45732 | C55: Expenses | E55: 25
A56: 45732 | C56: Staff Salary | E56: 3000 | G56: Advance
A57: 45733 | B57: GST-044 | C57: Sales | D57: 720
A58: 45733 | B58: GST-045 | C58: Sales | D58: 840
A59: 45733 | B59: GST-046 | C59: Sales | D59: 560
A60: 45733 | C60: Ginger Purchase | E60: 2250 | G60: 56Kgs *38.39
A61: 45733 | B61: GST-047 | C61: Sales | D61: 2460
A62: 45733 | C62: Expenses | E62: 335
A63: 45734 | B63: GST-048 | C63: Sales | D63: 6315
A64: 45734 | B64: GST-049 | C64: Sales | D64: 240
A65: 45734 | C65: Expenses | E65: 50
A66: 45735 | B66: GST-050 | C66: Sales | D66: 5685
A67: 45735 | B67: GST-051 | C67: Sales | D67: 1200
A68: 45735 | C68: Ginger Purchase | E68: 2250 | G68: 56Kgs *38.39
A69: 45735 | C69: Wifi Bill | E69: 550
A70: 45735 | C70: Expenses | E70: 350
A71: 45736 | B71: GST-052 | C71: Sales | D71: 1200
A72: 45736 | B72: GST-053 | C72: Sales | D72: 650
A73: 45736 | B73: INV-001 | C73: Sales | D73: 3820
A74: 45736 | C74: Ginger Purchase | E74: 2250 | G74: 56Kgs *38.39
A75: 45736 | C75: Expenses | E75: 160
A76: 45737 | B76: INV-002 | C76: Sales | D76: 4750
A77: 45737 | C77: Ginger Purchase | E77: 2250 | G77: 56Kgs *38.39
A78: 45737 | C78: Expenses | E78: 250 | G78: Electrician & Tea
A79: 45738 | C79: Expenses | E79: 440 | G79: Pouch purchase
A80: 45738 | B80: INV-003 | C80: Sales | D80: 340
A81: 45738 | C81: Ginger Purchase | E81: 250 | G81: 5kgs * 50Rs kg
A82: 45738 | C82: Garlic Purchase | E82: 750 | G82: 10kgs *75Rs kg
A83: 45738 | C83: Garlic Purchase | E83: 13390 | G83: 165kg * 80Rs
A84: 45738 | C84: Expenses | E84: 50
A85: 45738 | B85: INV-004 | C85: Sales | D85: 6460
A86: 45739 | B86: INV-005 | C86: Sales | D86: 6670
A87: 45739 | C87: Petrol | E87: 300
A88: 45740 | C88: Ginger Purchase | E88: 2250 | G88: 56Kgs *38.39
A89: 45740 | C89: Staff Salary | E89: 2610 | G89: Siva Malar
A90: 45740 | C90: Staff Salary | E90: 5310 | G90: Chitra
A91: 45740 | B91: INV-006 | C91: Sales | D91: 1800
A92: 45740 | B92: INV-007 | C92: Sales | D92: 7620
A93: 45740 | B93: INV-008 | C93: Sales | D93: 40
A94: 45740 | C94: Expenses | E94: 205
A95: 45741 | B95: INV-009 | C95: Sales | D95: 7715
A96: 45741 | B96: INV-010 | C96: Sales | D96: 180
A97: 45741 | C97: Ginger Purchase | E97: 2250 | G97: 56Kgs *38.39
A98: 45741 | C98: Expenses | E98: 150
A99: 45742 | B99: INV-011 | C99: Sales | D99: 12375
A100: 45742 | B100: INV-012 | C100: Sales | D100: 190
...

Sheet Apr 2025 - Sales
A1: Date | B1: Invoice No | C1: Description | D1: Sales | E1: Expences | F1: Credit | G1: Remarks
A2: 45748 | C2: Opening Balance | D2: ='Mar 2025 - Sales'!D132 -> 63848
A3: 45748 | C3: March Profit Share Paid | E3: 20460
A4: 45748 | B4: INV-024 | C4: Sales | D4: 1115
A5: 45748 | C5: Expences | E5: 789
A6: 45749 | B6: INV-025 | C6: Sales | D6: 2295
A7: 45749 | C7: Expences | E7: 50
A8: 45750 | B8: INV-026 | C8: Sales | D8: 2350
A9: 45750 | B9: INV-027 | C9: Sales | D9: 3250
A10: 45750 | C10: Expences | E10: 50
A11: 45751 | C11: Ginger Purchase | E11: 2150 | I11: Row Labels | J11: Sum of Sales | K11: Sum of Expences
A12: 45751 | B12: INV-028 | C12: Sales | D12: 4260 | I12: Bills | K12: 19884
A13: 45751 | C13: Petrol | E13: 300 | I13: Expences | K13: 6384
A14: 45751 | C14: Expences | E14: 50 | I14: Garlic Purchase | K14: 32855
A15: 45752 | B15: INV-029 | C15: Sales | D15: 3795 | I15: Ginger Purchase | K15: 13650
A16: 45753 | B16: INV-030 | C16: Sales | D16: 1955 | I16: March Profit Share Paid | K16: 20460
A17: 45753 | B17: INV-031 | C17: Sales | D17: 480 | I17: Opening Balance | J17: 63848
A18: 45754 | B18: INV-032 | C18: Sales | D18: 350 | I18: Others
A19: 45754 | B19: INV-033 | C19: Sales | D19: 755 | I19: Petrol | K19: 2100
A20: 45754 | C20: Expences | E20: 50 | I20: Rent | K20: 9000
A21: 45755 | B21: INV-034 | C21: Sales | D21: 2330 | I21: Sales | J21: 105060
A22: 45755 | B22: INV-035 | C22: Sales | D22: 480 | I22: Staff Salary | K22: 10500
A23: 45756 | C23: Petrol | E23: 300 | I23: (blank)
A24: 45756 | C24: Expences | E24: 280 | I24: Grand Total | J24: 168908 | K24: 114833
A25: 45757 | B25: INV-036 | C25: Sales | D25: 1325
A26: 45757 | B26: INV-037 | C26: Sales | D26: 3120
A27: 45758 | C27: Garlic Purchase | E27: 880
A28: 45758 | C28: Ginger Purchase | E28: 750
A29: 45758 | C29: Expences | E29: 397
A30: 45758 | B30: INV-038 | C30: Sales | D30: 5310
A31: 45758 | B31: INV-039 | C31: Sales | D31: 640
A32: 45759 | C32: Ginger Purchase | E32: 2150
A33: 45759 | C33: Expences | E33: 50
A34: 45759 | B34: INV-040 | C34: Sales | D34: 5020
A35: 45760 | B35: INV-041 | C35: Sales | D35: 3690
A36: 45760 | C36: Petrol | E36: 300
A37: 45761 | B37: INV-042 | C37: Sales | D37: 2610
A38: 45761 | C38: Rent | E38: 9000
A39: 45761 | C39: Expences | E39: 25
A40: 45762 | C40: Garlic Purchase | E40: 16575
A41: 45762 | C41: Ginger Purchase | E41: 2150
A42: 45762 | B42: INV-043 | C42: Sales | D42: 800
A43: 45762 | C43: Expences | E43: 50
A44: 45763 | B44: INV-044 | C44: Sales | D44: 2580
A45: 45763 | C45: Expences | E45: 25
A46: 45764 | B46: INV-045 | C46: Sales | D46: 160
A47: 45764 | B47: INV-046 | C47: Sales | D47: 3185
A48: 45764 | C48: Petrol | E48: 300
A49: 45765 | B49: INV-047 | C49: Sales | D49: 290
A50: 45765 | B50: INV-048 | C50: Sales | D50: 3550
A51: 45765 | C51: Expences | E51: 50
A52: 45765 | C52: Bills | E52: 550
A53: 45766 | C53: Expences | E53: 100
A54: 45766 | C54: Ginger Purchase | E54: 2150
A55: 45766 | B55: INV-049 | C55: Sales | D55: 5825
A56: 45766 | B56: INV-050 | C56: Others | G56: NFS
A57: 45766 | B57: INV-051 | C57: Sales | D57: 3500
A58: 45767 | B58: INV-052 | C58: Sales
A59: 45767 | B59: INV-053 | C59: Sales | D59: 1240
A60: 45767 | C60: Expences | E60: 165
A61: 45768 | B61: INV-054 | C61: Sales | D61: 2190
A62: 45768 | B62: INV-055 | C62: Sales | D62: 180
A63: 45768 | B63: INV-056 | C63: Others | G63: NFS
A64: 45768 | C64: Petrol | E64: 300
A65: 45768 | C65: Expences | E65: 903
A66: 45769 | C66: Bills | E66: 19334
A67: 45769 | B67: INV-057 | C67: Sales | D67: 1725
A68: 45769 | B68: INV-058 | C68: Sales | D68: 760
A69: 45769 | C69: Garlic Purchase | E69: 15400
A70: 45769 | C70: Expences | E70: 50
A71: 45770 | C71: Ginger Purchase | E71: 2150
A72: 45770 | B72: INV-059 | C72: Sales | D72: 5570
A73: 45770 | B73: INV-060 | C73: Sales | D73: 80
A74: 45770 | B74: INV-061 | C74: Sales | D74: 560
A75: 45770 | C75: Expences | E75: 50
A76: 45771 | B76: INV-062 | C76: Sales | D76: 5305
A77: 45771 | B77: INV-063 | C77: Sales | G77: NFS
A78: 45771 | C78: Expences | E78: 50
A79: 45771 | C79: Petrol | E79: 300
A80: 45772 | B80: INV-064 | C80: Sales | D80: 2825
A81: 45772 | B81: INV-065 | C81: Sales | G81: NFS
A82: 45772 | C82: Expences | E82: 50
A83: 45773 | C83: Expences | E83: 25
A84: 45773 | C84: Ginger Purchase | E84: 2150
A85: 45773 | B85: INV-066 | C85: Sales | D85: 120
A86: 45773 | B86: INV-067 | C86: Sales | D86: 4100
A87: 45774 | B87: INV-068 | C87: Sales | D87: 3450
A88: 45775 | C88: Petrol | E88: 300
A89: 45775 | C89: Expences | E89: 75
A90: 45775 | B90: INV-069 | C90: Sales | D90: 40
A91: 45775 | B91: INV-070 | C91: Sales | D91: 2375
A92: 45775 | B92: INV-071 | C92: Sales | D92: 340
A93: 45775 | B93: INV-072 | G93: NFS
A94: 45776 | C94: Expences | E94: 50
A95: 45776 | C95: Sales | D95: 2950
A96: 45777 | C96: Expences | E96: 3000
A97: 45777 | B97: INV-075 | C97: Sales | D97: 40
A98: 45777 | B98: INV-076 | C98: Sales | D98: 3990
A99: 45777 | B99: INV-077 | C99: Sales | D99: 2200
A100: 45777 | B100: INV-078 | C100: Sales | G100: NFS
...

Sheet May 2025 - Sales
A1: Date | B1: Invoice No | C1: Description | D1: Sales | E1: Expences | F1: Credit | G1: Remarks
A2: 45778 | C2: Opening Balance | D2: ='Apr 2025 - Sales'!D108 -> 54075
A3: 45778 | C3: Expences | E3: 630
A4: 45778 | C4: Ginger Purchase | E4: 1900
A5: 45778 | B5: INV-079 | C5: Sales | D5: 1440
A6: 45778 | B6: INV-080 | C6: Sales | D6: 2100
A7: 45779 | C7: Garlic Purchase | E7: 17930
A8: 45779 | B8: INV-081 | C8: Sales | D8: 2925
A9: 45779 | C9: Expences | E9: 123
A10: 45780 | B10: INV-082 | C10: Sales | D10: 1150 | I10: Row Labels | J10: Sum of Sales | K10: Sum of Expences
A11: 45780 | C11: Expences | E11: 1052 | I11: Opening Balance | J11: 54075
A12: 45781 | B12: INV-083 | C12: Sales | D12: 4570 | I12: (blank)
A13: 45781 | C13: Petrol | E13: 300 | I13: Expences | K13: 47672
A14: 45782 | C14: Expences | E14: 225 | G14: 30th April missing | I14: Ginger Purchase | K14: 22475
A15: 45782 | C15: Expences | E15: 650 | I15: Sales | J15: 133160
A16: 45782 | B16: INV-084 | C16: Sales | D16: 3525 | I16: Garlic Purchase | K16: 62595
A17: 45782 | B17: INV-085 | C17: Sales | D17: 40 | I17: Petrol | K17: 1900
A18: 45783 | C18: Rent | E18: 9000 | I18: Rent | K18: 9000
A19: 45783 | C19: Ginger Purchase | E19: 1750 | I19: Staff Salary | K19: 9250
A20: 45783 | C20: Expences | E20: 25 | I20: Bills | K20: 550
A21: 45783 | B21: INV-086 | C21: Sales | D21: 1990 | I21: Others | K21: 1120
A22: 45783 | B22: INV-087 | C22: Sales | D22: 80 | I22: Grand Total | J22: 187235 | K22: 154562
A23: 45784 | C23: Expences | E23: 2360 | G23: Barcode Purchase 2 Nos
A24: 45784 | C24: Expences | E24: 25
A25: 45784 | B25: INV-088 | C25: Sales | D25: 700
A26: 45784 | B26: INV-089 | C26: Sales | D26: 2925
A27: 45785 | C27: Petrol | E27: 300
A28: 45785 | C28: Expences | E28: 18500 | G28: Freezer purchase
A29: 45785 | C29: Expences | E29: 50
A30: 45785 | C30: Staff Salary | E30: 3000 | G30: Siva Malar Salary advance
A31: 45785 | B31: INV-090 | C31: Sales | D31: 3225
A32: 45786 | B32: INV-091 | C32: Sales | D32: 1415
A33: 45786 | B33: INV-091 | C33: Sales | D33: 450
A34: 45786 | C34: Expences | E34: 1110
A35: 45787 | C35: Ginger Purchase | E35: 1850
A36: 45787 | C36: Expences | E36: 25
A37: 45787 | B37: INV-093 | C37: Sales | D37: 8300
A38: 45788 | B38: INV-094 | C38: Sales | D38: 1920
A39: 45788 | B39: INV-095 | C39: Sales | D39: 120
A40: 45788 | C40: Expences | E40: 14200 | G40: Freezer purchase kkl
A41: 45788 | C41: Expences | E41: 140
A42: 45789 | B42: INV-096 | C42: Sales | D42: 2650
A43: 45789 | B43: INV-097 | C43: Sales | D43: 280
A44: 45789 | C44: Expences | E44: 165
A45: 45790 | B45: INV-098 | C45: Sales | D45: 2470
A46: 45790 | B46: INV-099 | C46: Sales | D46: 600
A47: 45790 | B47: INV-100 | C47: Sales | D47: 150
A48: 45790 | C48: Petrol | E48: 300
A49: 45790 | C49: Staff Salary | E49: 300 | G49: Temp Staff
A50: 45790 | C50: Expences | E50: 20
A51: 45791 | C51: Garlic Purchase | E51: 42865
A52: 45791 | C52: Ginger Purchase | E52: 1950
A53: 45791 | B53: INV-101 | C53: Sales | D53: 2160
A54: 45791 | B54: INV-102 | C54: Sales | D54: 840
A55: 45791 | B55: INV-103 | C55: Sales | D55: 470
A56: 45791 | C56: Expences | E56: 186
A57: 45792 | B57: INV-104 | C57: Sales | D57: 6680
A58: 45792 | B58: INV-105 | C58: Sales | D58: 100
A59: 45792 | C59: Expences | E59: 20
A60: 45793 | B60: INV-106 | C60: Sales | D60: 80
A61: 45793 | B61: INV-107 | C61: Sales | D61: 1800
A62: 45793 | B62: INV-108 | C62: Sales | D62: 720
A63: 45793 | C63: Expences | E63: 70
A64: 45793 | C64: Expences | E64: 3700 | G64: EB KV increment
A65: 45794 | B65: INV-109 | C65: Sales | D65: 2420
A66: 45794 | B66: INV-110 | C66: Sales | D66: 1190
A67: 45794 | B67: INV-111 | C67: Sales | D67: 700
A68: 45794 | C68: Expences | E68: 220
A69: 45794 | C69: Petrol | E69: 300
A70: 45795 | B70: INV-112 | C70: Sales | D70: 3525
A71: 45796 | C71: Ginger Purchase | E71: 8750
A72: 45796 | B72: INV-113 | C72: Sales | D72: 340
A73: 45796 | B73: INV-114 | C73: Sales | D73: 280
A74: 45796 | B74: INV-115 | C74: Sales | D74: 700
A75: 45796 | C75: Bills | E75: 550 | G75: Wifi Bill
A76: 45796 | C76: Expences | E76: 20
A77: 45797 | B77: INV-116 | C77: Sales | D77: 230
A78: 45797 | B78: INV-117 | C78: Sales | D78: 5270
A79: 45797 | B79: INV-118 | C79: Sales | D79: 2430
A80: 45797 | B80: INV-119 | C80: Sales | D80: 1020
A81: 45797 | C81: Staff Salary | E81: 200 | G81: Temp Staff
A82: 45797 | C82: Expences | E82: 220
A83: 45797 | C83: Others | E83: 1120 | G83: 500 Rs pathiram x2
A84: 45798 | B84: INV-120 | C84: Sales | D84: 960
A85: 45798 | B85: INV-121 | C85: Sales | D85: 850
A86: 45798 | C86: Expences | E86: 20
A87: 45799 | B87: INV-122 | C87: Sales | D87: 1080
A88: 45799 | B88: INV-123 | C88: Sales | D88: 100
A89: 45799 | C89: Expences | E89: 75
A90: 45800 | B90: INV-124 | C90: Sales | D90: 7120
A91: 45800 | B91: INV-125 | C91: Sales | D91: 800
A92: 45800 | C92: Garlic Purchase | E92: 1500
A93: 45800 | C93: Petrol | E93: 400
A94: 45800 | C94: Expences | E94: 220
A95: 45801 | B95: INV-126 | C95: Sales | D95: 5310
A96: 45801 | B96: INV-127 | C96: Sales | D96: 3920
A97: 45801 | C97: Expences | E97: 390
A98: 45802 | C98: Ginger Purchase | E98: 2150
A99: 45802 | B99: INV-128 | C99: Sales | D99: 2400
A100: 45802 | B100: INV-129 | C100: Sales | D100: 720
...

Sheet June 2025 - Sales
A1: Date | B1: Invoice No | C1: Description | D1: Sales | E1: Expences | F1: Credit | G1: Remarks
A2: 45809 | C2: Opening Balance | D2: ='May 2025 - Sales'!D137 -> 32673
A3: 45809 | C3: Ginger Purchase | E3: 2500
A4: 45809 | B4: INV-147 | C4: Sales | D4: 1760
A5: 45809 | B5: INV-148 | C5: Sales | D5: 2600
A6: 45809 | C6: Expences | E6: 20
A7: 45809 | C7: Staff Salary | E7: 3000 | G7: Siva Malar Advance
A8: 45810 | B8: INV-149 | C8: Sales | D8: 120
A9: 45810 | B9: INV-150 | C9: Sales | D9: 1900
A10: 45810 | C10: Expences | E10: 210
A11: 45810 | C11: Petrol | E11: 300 | I11: Row Labels | J11: Sum of Sales | K11: Sum of Expences
A12: 45811 | C12: Ginger Purchase | E12: 2400 | I12: Opening Balance | J12: 32673
A13: 45811 | B13: INV-151 | C13: Sales | D13: 40 | I13: Ginger Purchase | K13: 18600
A14: 45811 | B14: INV-152 | C14: Sales | D14: 560 | I14: Sales | J14: 126385
A15: 45811 | B15: INV-153 | C15: Sales | D15: 1400 | I15: Expences | K15: 10525
A16: 45811 | C16: Expences | E16: 75 | I16: Petrol | K16: 1600
A17: 45812 | B17: INV-154 | C17: Sales | D17: 3540 | I17: Garlic Purchase | K17: 111892
A18: 45812 | B18: INV-155 | C18: Sales | D18: 1560 | I18: Staff Salary | K18: 10200
A19: 45812 | B19: INV-156 | C19: Sales | D19: 2780 | I19: Rent | K19: 9000
A20: 45812 | C20: Expences | E20: 50 | I20: Bills | K20: 11852
A21: 45813 | C21: Garlic Purchase | E21: 34610 | G21: Nilaa WH | I21: Advance | J21: 0
A22: 45813 | C22: Staff Salary | E22: 300 | G22: Temp | I22: Grand Total | J22: 159058 | K22: 173669
A23: 45813 | C23: Expences | E23: 25
A24: 45813 | B24: INV-157 | C24: Sales | D24: 4300
A25: 45813 | B25: INV-158 | C25: Sales | D25: 1950
A26: 45813 | B26: INV-159 | C26: Sales | D26: 790
A27: 45813 | B27: INV-160 | C27: Sales | D27: 660
A28: 45814 | B28: INV-161 | C28: Sales | D28: 120
A29: 45814 | B29: INV-162 | C29: Sales | D29: 2650 | I29: Summary of Sales and Expences - June 2025
A30: 45814 | B30: INV-163 | C30: Sales | D30: 100 | I30: Row Labels | J30: Sum of Sales | K30: Sum of Expences
A31: 45814 | B31: INV-164 | C31: Sales | D31: 100 | I31: Advance | J31: 0
A32: 45814 | B32: INV-165 | C32: Sales | D32: 1280 | I32: Bills | K32: 11852
A33: 45814 | C33: Staff Salary | E33: 100 | I33: Expences | K33: 10335
A34: 45814 | C34: Expences | E34: 50 | I34: Garlic Purchase | K34: 111892
A35: 45814 | C35: Ginger Purchase | E35: 2400 | I35: Ginger Purchase | K35: 18600
A36: 45815 | B36: INV-166 | C36: Sales | D36: 1915 | I36: Opening Balance | J36: 32673
A37: 45815 | C37: Expences | E37: 50 | I37: Petrol | K37: 1600
A38: 45816 | B38: INV-167 | C38: Sales | D38: 7380 | I38: Rent | K38: 9000
A39: 45816 | B39: INV-168 | C39: Sales | D39: 2245 | I39: Sales | J39: 126385
A40: 45816 | C40: Petrol | E40: 300 | I40: Staff Salary | K40: 10200
A41: 45816 | C41: Staff Salary | E41: 50 | I41: Grand Total | J41: 159058 | K41: 173479
A42: 45817 | C42: Ginger Purchase | E42: 2300
A43: 45817 | C43: Expences | E43: 50 | I43: Net Revenue | J43: =J39-K41 -> -47094
A44: 45817 | B44: INV-169 | C44: Sales | D44: 280 | I44: Net Balance | J44: =J41-K41 -> -14421
A45: 45817 | B45: INV-170 | C45: Sales | D45: 240 | I45: Deficit | J45: =J44-'Feb 2025 - Sales'!C2 -> -57349
A46: 45817 | B46: INV-171 | C46: Sales | D46: 380
A47: 45818 | B47: INV-172 | C47: Sales | D47: 850
A48: 45818 | B48: INV-173 | C48: Sales | D48: 880
A49: 45818 | C49: Expences | E49: 220
A50: 45819 | B50: INV-174 | C50: Sales | D50: 3650
A51: 45819 | B51: INV-175 | C51: Sales | D51: 200
A52: 45819 | B52: INV-176 | C52: Sales | D52: 880
A53: 45819 | C53: Rent | E53: 9000
A54: 45819 | C54: Expences | E54: 1495
A55: 45820 | B55: INV-177 | C55: Sales | D55: 3165
A56: 45820 | B56: INV-178 | C56: Sales | D56: 80
A57: 45820 | C57: Expences | E57: 75
A58: 45821 | B58: INV-179 | C58: Sales | D58: 40
A59: 45821 | B59: INV-180 | C59: Sales | D59: 1900
A60: 45821 | B60: INV-181 | C60: Sales | D60: 3295
A61: 45821 | C61: Expences | E61: 210
A62: 45821 | C62: Petrol | E62: 300
A63: 45822 | B63: INV-182 | C63: Sales | D63: 180
A64: 45822 | B64: INV-183 | C64: Sales | D64: 610
A65: 45822 | B65: INV-184 | C65: Sales | D65: 100
A66: 45822 | B66: INV-185 | C66: Sales | D66: 1240
A67: 45822 | C67: Expences | E67: 409
A68: 45822 | C68: Ginger Purchase | E68: 2300
A69: 45823 | C69: Advance | D69: 0 | G69: Sulaiman kaka order
A70: 45823 | B70: INV-186 | C70: Sales | D70: 4010
A71: 45823 | B71: INV-187 | C71: Sales | D71: 1440
A72: 45824 | B72: INV-188 | C72: Sales | D72: 1020
A73: 45824 | B73: INV-189 | C73: Sales | D73: 140
A74: 45824 | B74: INV-190 | C74: Sales | D74: 1900
A75: 45825 | C75: Bills | E75: 550 | G75: Wi-fi Bill
A76: 45825 | B76: INV-191 | C76: Sales | D76: 1240
A77: 45825 | B77: INV-192 | C77: Sales | D77: 260
A78: 45825 | C78: Expences | E78: 50
A79: 45826 | B79: INV-193 | C79: Sales | D79: 880
A80: 45826 | B80: INV-194 | C80: Sales | D80: 430
A81: 45826 | B81: INV-195 | C81: Sales | D81: 80
A82: 45826 | C82: Petrol | E82: 300
A83: 45826 | C83: Expences | E83: 210
A84: 45827 | B84: INV-196 | C84: Sales | D84: 3100
A85: 45827 | B85: INV-197 | C85: Sales | D85: 480
A86: 45827 | C86: Expences | E86: 25
A87: 45828 | B87: INV-198 | C87: Sales | D87: 4555
A88: 45828 | B88: INV-199 | C88: Sales | D88: 300
A89: 45828 | B89: INV-200 | C89: Sales | D89: 40
A90: 45828 | C90: Expences | E90: 50
A91: 45828 | C91: Garlic Purchase | E91: 1710 | G91: Rs 90 per kg
A92: 45829 | C92: Bills | E92: 11302
A93: 45829 | C93: Ginger Purchase | E93: 2300
A94: 45829 | B94: INV-201 | C94: Sales | D94: 3520
A95: 45829 | B95: INV-202 | C95: Sales | D95: 6750
A96: 45829 | B96: INV-203 | C96: Sales | D96: 2840
A97: 45829 | B97: INV-204 | C97: Sales | D97: 700 | I97: Sulaiman | J97: 202
A98: 45829 | C98: Expences | E98: 300
A99: 45830 | B99: INV-205 | C99: Sales | D99: 1850
A100: 45830 | B100: INV-206 | C100: Sales | D100: 840
...

Sheet July 2025 - Sales
A1: Date | B1: Invoice No | C1: Description | D1: Sales | E1: Expences | F1: Bill To | G1: Credit | H1: Remarks
A2: 45839 | C2: Opening Balance | D2: ='June 2025 - Sales'!D147 -> -14611
A3: 45839 | B3: INV-234 | C3: Sales | D3: 410 | F3: Cash
A4: 45839 | B4: INV-235 | C4: Sales | D4: 1330 | F4: Riluwan(Nagore)
A5: 45839 | B5: INV-236 | C5: Sales | D5: 240 | F5: Ansari
A6: 45839 | C6: Expences | E6: 210
A7: 45840 | C7: Ginger Purchase | E7: 2200
A8: 45840 | C8: Expences | E8: 447
A9: 45840 | B9: INV-237 | C9: Sales | D9: 3000 | F9: Riluwan(Nagore)
A10: 45840 | B10: INV-238 | C10: Sales | D10: 80 | F10: Cash
A11: 45841 | C11: Staff Salary | E11: 2000 | H11: Salary Advance - Malar | J11: Row Labels | K11: Sum of Sales | L11: Sum of Expences
A12: 45841 | B12: INV-239 | C12: Sales | D12: 3630 | F12: Riluwan(Nagore) | J12: Opening Balance | K12: -14611
A13: 45841 | B13: INV-240 | C13: Sales | D13: 40 | F13: Cash | J13: Sales | K13: 164755
A14: 45841 | C14: Expences | E14: 25 | J14: Expences | L14: 8384
A15: 45842 | B15: INV-241 | C15: Sales | D15: 40 | F15: Cash | J15: Ginger Purchase | L15: 25600
A16: 45842 | B16: INV-242 | C16: Sales | D16: 3310 | F16: Market Shop | J16: Staff Salary | L16: 10750
A17: 45842 | B17: INV-243 | C17: Sales | D17: 280 | F17: Faisal(Nagai) | J17: Petrol | L17: 1400
A18: 45842 | C18: Expences | E18: 25 | J18: Garlic Purchase | L18: 30735
A19: 45842 | C19: Petrol | E19: 400 | J19: Rent | L19: 9000
A20: 45843 | B20: INV-244 | C20: Sales | D20: 700 | F20: Faisal(Nagai) | J20: Bills | L20: 900
A21: 45843 | B21: INV-245 | C21: Sales | D21: 720 | F21: Market Shop | J21: Others | L21: 2727
A22: 45843 | B22: INV-246 | C22: Sales | D22: 1900 | F22: Riluwan(Nagore) | J22: Grand Total | K22: 150144 | L22: 89496
A23: 45844 | B23: INV-247 | C23: Sales | D23: 480 | F23: Ansari
A24: 45844 | B24: INV-248 | C24: Sales | D24: 180 | F24: Market Shop
A25: 45844 | B25: INV-249 | C25: Sales | D25: 1275 | F25: Riluwan(Nagore) | J25: Gross Revenue | K25: 164755
A26: 45844 | C26: Rent | E26: 9000 | J26: Total | K26: 150144 | L26: 89246
A27: 45845 | B27: INV-250 | C27: Sales | D27: 2240 | F27: Riluwan(Nagore)
A28: 45845 | B28: INV-251 | C28: Sales | D28: 600 | F28: Market Shop | J28: Net Revenue | K28: 75509
A29: 45845 | B29: INV-252 | C29: Sales | D29: 100 | F29: Ansari | J29: Net Balance | K29: 60898
A30: 45845 | C30: Expences | E30: 50
A31: 45846 | B31: INV-253 | C31: Sales | D31: 80 | F31: Cash | J31: Deficit | K31: 17970
A32: 45846 | B32: INV-254 | C32: Sales | D32: 100 | F32: Hassan
A33: 45846 | B33: INV-255 | C33: Sales | D33: 100 | F33: Ansari
A34: 45846 | B34: INV-256 | C34: Sales | D34: 1260 | F34: Market Shop
A35: 45846 | C35: Garlic Purchase | E35: 1800
A36: 45846 | C36: Expences | E36: 25
A37: 45847 | B37: INV-257 | C37: Sales | D37: 3100 | F37: Riluwan(Nagore)
A38: 45847 | B38: INV-258 | C38: Sales | D38: 1650 | F38: Market Shop
A39: 45848 | B39: INV-259 | C39: Sales | D39: 720 | F39: Market Shop
A40: 45848 | B40: INV-260 | C40: Sales | D40: 240 | F40: Ansari
A41: 45848 | B41: INV-261 | C41: Sales | D41: 1900 | F41: Riluwan(Nagore)
A42: 45848 | C42: Expences | E42: 185
A43: 45849 | C43: Garlic Purchase | E43: 3960
A44: 45849 | C44: Ginger Purchase | E44: 4400
A45: 45849 | B45: INV-262 | C45: Sales | D45: 5490 | F45: Riluwan(Nagore)
A46: 45849 | B46: INV-263 | C46: Sales | D46: 2880 | F46: Market Shop
A47: 45849 | B47: INV-264 | C47: Sales | D47: 80 | F47: Cash
A48: 45849 | B48: INV-265 | C48: Sales | D48: 8000 | F48: Ansari | H48: MGK - Paid
A49: 45849 | B49: INV-266 | C49: Sales | D49: 1260 | F49: Faisal(Nagai)
A50: 45849 | C50: Staff Salary | E50: 300
A51: 45849 | C51: Petrol | E51: 400
A52: 45849 | C52: Expences | E52: 758
A53: 45850 | C53: Garlic Purchase | E53: 900
A54: 45850 | C54: Ginger Purchase | E54: 2100
A55: 45850 | B55: INV-267 | C55: Sales | D55: 4800 | F55: Halidh Cook
A56: 45850 | B56: INV-268 | C56: Sales | D56: 600 | F56: Market Shop
A57: 45850 | B57: INV-269 | C57: Sales | D57: 12480 | F57: Riluwan(Nagore)
A58: 45850 | C58: Staff Salary | E58: 300
A59: 45850 | C59: Expences | E59: 238
A60: 45851 | B60: INV-270 | C60: Sales | D60: 4175 | F60: Riluwan(Nagore)
A61: 45851 | B61: INV-271 | C61: Sales | D61: 1020 | F61: Market Shop
A62: 45852 | B62: INV-272 | C62: Sales | D62: 3985 | F62: Riluwan(Nagore)
A63: 45852 | B63: INV-273 | C63: Sales | D63: 40 | F63: Cash
A64: 45852 | C64: Expences | E64: 210
A65: 45853 | C65: Garlic Purchase | E65: 900
A66: 45853 | C66: Ginger Purchase | E66: 2200
A67: 45853 | B67: INV-274 | C67: Sales | D67: 1200 | F67: Riluwan(Nagore)
A68: 45853 | B68: INV-275 | C68: Sales | D68: 40 | F68: Cash
A69: 45853 | B69: INV-276 | C69: Sales | D69: 180 | F69: Market Shop
A70: 45853 | B70: INV-277 | C70: Sales | D70: 420 | F70: Faisal(Nagai)
A71: 45853 | C71: Expences | E71: 45
A72: 45854 | B72: INV-278 | C72: Sales | D72: 150 | F72: Cash
A73: 45854 | B73: INV-279 | C73: Sales | D73: 2500 | F73: Riluwan(Nagore)
A74: 45854 | C74: Expences | E74: 25
A75: 45855 | B75: INV-280 | C75: Sales | D75: 3855 | F75: Riluwan(Nagore)
A76: 45855 | C76: Expences | E76: 25
A77: 45855 | C77: Bills | E77: 550 | H77: Wifi Bill
A78: 45856 | B78: INV-281 | C78: Sales | D78: 2370 | F78: Riluwan(Nagore)
A79: 45856 | B79: INV-282 | C79: Sales | D79: 170 | F79: Cash
A80: 45856 | B80: INV-283 | C80: Sales | D80: 910 | F80: Market Shop
A81: 45856 | C81: Petrol | E81: 400
A82: 45856 | C82: Expences | E82: 50
A83: 45857 | C83: Ginger Purchase | E83: 2500
A84: 45857 | C84: Garlic Purchase | E84: 900
A85: 45857 | B85: INV-284 | C85: Sales | D85: 1930 | F85: Market Shop
A86: 45857 | B86: INV-285 | C86: Sales | D86: 10630 | F86: Riluwan(Nagore)
A87: 45857 | B87: INV-286 | C87: Sales | D87: 4500 | F87: Ansari
A88: 45857 | C88: Staff Salary | E88: 100 | H88: Temp Staff
A89: 45857 | C89: Expences | E89: 500
A90: 45858 | B90: INV-287 | C90: Sales | D90: 1850 | F90: Riluwan(Nagore)
A91: 45858 | C91: Expences | E91: 30
A92: 45858 | B92: INV-288 | C92: Sales | D92: 920 | F92: Market Shop
A93: 45858 | B93: INV-289 | C93: Sales | D93: 480 | F93: Cash
A94: 45859 | B94: INV-290 | C94: Sales | D94: 5645 | F94: Riluwan(Nagore)
A95: 45859 | B95: INV-291 | C95: Sales | D95: 1450 | F95: Cash
A96: 45859 | C96: Ginger Purchase | E96: 2800
A97: 45859 | C97: Garlic Purchase | E97: 900
A98: 45859 | B98: INV-292 | C98: Sales | D98: 1200 | F98: Market Shop
A99: 45860 | B99: INV-293 | C99: Sales | D99: 750 | F99: Cash
A100: 45860 | B100: INV-294 | C100: Sales | D100: 280 | F100: Cash
...

Sheet Aug 2025 - Sales
A1: Date | B1: Invoice No | C1: Description | D1: Sales | E1: Expences | F1: Bill To | G1: Variety | H1: Unit Price | I1: Transport cost | J1: Qty | K1: Supplier | L1: Credit | M1: Remarks
C2: Opening Balance | D2: ='July 2025 - Sales'!D150 -> 60648
A3: 45870 | B3: INV-322 | C3: Sales | D3: 340 | F3: Cash
A4: 45870 | B4: INV-323 | C4: Sales | D4: 500 | F4: Riluwan(Nagore)
A5: 45870 | B5: INV-324 | C5: Sales | D5: 100 | F5: Ansari
A6: 45871 | B6: INV-325 | C6: Sales | D6: 350 | F6: Cash
A7: 45871 | B7: INV-326 | C7: Sales | D7: 1920 | F7: Market Shop
A8: 45871 | B8: INV-327 | C8: Sales | D8: 210 | F8: Faisal(Nagai)
A9: 45871 | B9: P-53 | C9: Ginger Purchase | E9: 3900 | G9: Old Ginger | H9: 69.65 | J9: 56 | K9: Jakakodi Traders
A10: 45871 | C10: Expences | E10: 25
A11: 45872 | B11: INV-328 | C11: Sales | D11: 300 | F11: Cash
A12: 45872 | B12: INV-329 | C12: Sales | D12: 675 | F12: Market Shop
A13: 45872 | B13: INV-330 | C13: Sales | D13: 3500 | F13: Riluwan(Nagore)
A14: 45872 | B14: INV-331 | C14: Sales | D14: 2100 | F14: Ansari
A15: 45872 | B15: INV-332 | C15: Sales | D15: 1200 | F15: Cash
A16: 45872 | C16: Delivery charge | E16: 200 | M16: Nagai delivery
A17: 45873 | B17: INV-333 | C17: Sales | D17: 960 | F17: Cash
A18: 45873 | B18: INV-334 | C18: Sales | D18: 570 | F18: Market Shop
A19: 45873 | C19: Expences | E19: 210
A20: 45873 | C20: Petrol | E20: 400
A21: 45874 | B21: INV-335 | C21: Sales | D21: 620 | F21: Cash
A22: 45874 | B22: INV-336 | C22: Sales | D22: 4660 | F22: Market Shop
A23: 45874 | C23: Rent | E23: 9000
A24: 45874 | C24: Others | E24: 644 | M24: Pouch
A25: 45874 | C25: Others | E25: 400 | M25: Sticker 10 Sheets
A26: 45874 | C26: Expences | E26: 50
A27: 45875 | C27: Expences | E27: 50
A28: 45875 | C28: Others | E28: 70 | O28: Row Labels | P28: Sum of Sales | Q28: Sum of Expences
A29: 45875 | C29: Garlic Purchase | E29: 6270 | G29: Desi 4A | H29: 95 | J29: 66 | K29: Nilaa Wholesale Supplies | O29: Opening Balance | P29: 60648
A30: 45875 | C30: Ginger Purchase | E30: 3800 | G30: Old Ginger | H30: 67.85 | J30: 56 | K30: Jakakodi Traders | O30: Sales | P30: 173370
A31: 45875 | B31: INV-337 | C31: Sales | D31: 940 | F31: Cash | O31: Ginger Purchase | Q31: 42800
A32: 45875 | B32: INV-338 | C32: Sales | D32: 3520 | F32: Market Shop | O32: Expences | Q32: 1143
A33: 45877 | B33: INV-339 | C33: Sales | D33: 450 | F33: Cash | O33: Delivery charge | Q33: 1350
A34: 45877 | B34: INV-340 | C34: Sales | D34: 4170 | F34: Market Shop | O34: Petrol | Q34: 2000
A35: 45877 | B35: INV-341 | C35: Sales | D35: 1800 | F35: Barak Vegetables | O35: Rent | Q35: 9000
A36: 45877 | B36: INV-342 | C36: Sales | D36: 300 | F36: Faisal(Nagai) | O36: Others | Q36: 4399
A37: 45876 | B37: INV-343 | C37: Sales | D37: 5400 | F37: Ansari | O37: Garlic Purchase | Q37: 79255
A38: 45876 | B38: INV-344 | C38: Sales | D38: 6075 | F38: Market Shop | O38: Staff Salary | Q38: 11650
A39: 45876 | B39: INV-345 | C39: Sales | D39: 400 | F39: Cash | O39: Water Cane | Q39: 640
A40: 45876 | C40: Delivery charge | E40: 250 | O40: Bills | Q40: 13256
A41: 45877 | C41: Ginger Purchase | E41: 7600 | G41: Old Ginger | H41: 67.26 | J41: 113 | K41: Jakakodi Traders | O41: Marketting | Q41: 4000
A42: 45877 | C42: Garlic Purchase | E42: 3230 | G42: Desi 4A | H42: 95 | J42: 34 | K42: Nilaa Wholesale Supplies | O42: Packaging Material | Q42: 800
A43: 45877 | C43: Garlic Purchase | E43: 13855 | G43: Naatu Poondu | H43: 65 | J43: 197 | K43: Mass Traders | O43: Grand Total | P43: 234018 | Q43: 170293
A44: 45877 | C44: Delivery charge | E44: 100
A45: 45877 | C45: Expences | E45: 50
A46: 45878 | B46: INV-346 | C46: Sales | D46: 250 | F46: Cash
A47: 45878 | B47: INV-347 | C47: Sales | D47: 5005 | F47: Market Shop
A48: 45878 | B48: INV-348 | C48: Sales | D48: 13500 | F48: Ansari | M48: Shaha Malim
A49: 45878 | C49: Staff Salary | E49: 150
A50: 45878 | C50: Delivery charge | E50: 150
A51: 45878 | C51: Petrol | E51: 300
A52: 45878 | C52: Expences | E52: 50
A53: 45878 | C53: Water Cane | E53: 160
A54: 45879 | B54: INV-349 | C54: Sales | D54: 900 | F54: Cash
A55: 45879 | B55: INV-350 | C55: Sales | D55: 3600 | F55: Ansari
A56: 45879 | B56: INV-351 | C56: Sales | D56: 945 | F56: Market Shop
A57: 45879 | C57: Delivery charge | E57: 150
A58: 45880 | B58: INV-352 | C58: Sales | D58: 160 | F58: Cash
A59: 45880 | B59: INV-353 | C59: Sales | D59: 2210 | F59: Market Shop
A60: 45881 | C60: Ginger Purchase | E60: 4000 | G60: Old Ginger | H60: 80 | J60: 50 | K60: Jakakodi Traders
A61: 45881 | B61: INV-354 | C61: Sales | D61: 3250 | F61: Market Shop
A62: 45881 | B62: INV-355 | C62: Sales | D62: 900 | F62: Faisal(Nagai)
A63: 45881 | B63: INV-356 | C63: Sales | D63: 180 | F63: Cash
A64: 45881 | C64: Expences | E64: 50
A65: 45882 | B65: INV-357 | C65: Sales | D65: 240 | F65: Cash
A66: 45882 | B66: INV-358 | C66: Sales | D66: 1820 | F66: Nasar
A67: 45882 | B67: INV-359 | C67: Sales | D67: 1600 | F67: Ansari | M67: Sulaiman & Nagai
A68: 45882 | C68: Delivery charge | E68: 100
A69: 45882 | C69: Delivery charge | E69: 100
A70: 45882 | C70: Petrol | E70: 300
A71: 45883 | B71: INV-360 | C71: Sales | D71: 240 | F71: Cash
A72: 45883 | B72: INV-361 | C72: Sales | D72: 4610 | F72: Nasar
A73: 45883 | C73: Expences | E73: 50
A74: 45884 | B74: INV-362 | C74: Sales | D74: 290 | F74: Cash
A75: 45884 | B75: INV-363 | C75: Sales | D75: 3565 | F75: Nasar
A76: 45884 | B76: P-55 | C76: Ginger Purchase | E76: 4000 | G76: Old Ginger | H76: 80 | J76: 50 | K76: Jakakodi Traders
A77: 45884 | C77: Expences | E77: 50
A78: 45884 | C78: Water Cane | E78: 160
A79: 45884 | C79: Others | E79: 50
A80: 45885 | B80: INV-364 | C80: Sales | D80: 6815 | F80: Nasar
A81: 45885 | B81: INV-365 | C81: Sales | D81: 2080 | F81: Riluwan(Nagore)
A82: 45885 | B82: INV-366 | C82: Sales | D82: 4130 | F82: Nasar
A83: 45887 | B83: INV-367 | C83: Sales | D83: 200 | F83: Hassan
A84: 45887 | B84: INV-368 | C84: Sales | D84: 770 | F84: Cash
A85: 45887 | B85: INV-369 | C85: Sales | D85: 2545 | F85: Nasar
A86: 45888 | C86: Bills | E86: 550
A87: 45888 | B87: P-56 | C87: Ginger Purchase | E87: 3900 | G87: Old Ginger | H87: 78 | J87: 50 | K87: Jakakodi Traders
A88: 45888 | B88: INV-370 | C88: Sales | D88: 240 | F88: Cash
A89: 45888 | B89: INV-371 | C89: Sales | D89: 4010 | F89: Nasar
A90: 45889 | B90: INV-372 | C90: Sales | D90: 520 | F90: Cash
A91: 45889 | B91: INV-373 | C91: Sales | D91: 1110 | F91: Faisal(Nagai)
A92: 45889 | B92: INV-374 | C92: Sales | D92: 2990 | F92: Nasar
A93: 45889 | C93: Others | E93: 400 | M93: Sticker Printing
A94: 45889 | C94: Others | E94: 835 | M94: Ungal Kadai
A95: 45889 | C95: Expences | E95: 108
A96: 45890 | C96: Petrol | E96: 300
A97: 45890 | B97: INV-375 | C97: Sales | D97: 2280 | F97: Nasar
A98: 45890 | C98: Expences | E98: 50
A99: 45891 | C99: Garlic Purchase | E99: 31425 | G99: Naatu Poondu | H99: 75 | I99: 1800 | J99: 395 | K99: SVG Garlics
A100: 45891 | C100: Garlic Purchase | E100: 22975 | G100: Desi Bom size | H100: 125 | I100: 100 | J100: 183 | K100: Nilaa Wholesale Supplies
...

Sheet Sep 2025 - Sales 
A1: Date | B1: Invoice No | C1: Description | D1: Sales | E1: Expences | F1: Bill To | G1: Variety | H1: Unit Price | I1: Transport cost | J1: Qty | K1: Supplier | L1: Credit | M1: Remarks
C2: Opening Balance | D2: ='Aug 2025 - Sales'!D162 -> 63725
A3: 45901 | B3: INV-406 | C3: Sales | D3: 340 | F3: Cash
A4: 45901 | B4: INV-407 | C4: Sales | D4: 80 | F4: Hotel Noordeen
A5: 45901 | B5: INV-408 | C5: Sales | D5: 100 | F5: Ansari
A6: 45901 | B6: INV-409 | C6: Sales | D6: 400 | F6: Hassan
A7: 45901 | B7: INV-410 | C7: Sales | D7: 240 | F7: Maraikar Shop
A8: 45901 | B8: INV-411 | C8: Sales | D8: 240 | F8: REAL SUPER MARKET
A9: 45901 | B9: INV-412 | C9: Sales | D9: 1800 | F9: BILAL COOK
A10: 45901 | C10: Expences | E10: 50
A11: 45901 | C11: Packaging Material | E11: 400
A12: 45902 | C12: Ginger Purchase | E12: 3900 | G12: Old Ginger | H12: 78 | J12: 50 | K12: Jakakodi Traders
A13: 45902 | B13: INV-413 | C13: Sales | D13: 1200 | F13: DARBAR CATERING
A14: 45902 | B14: INV-414 | C14: Sales | D14: 1500 | F14: AL AZEEM CATERS & RESTAURANT
A15: 45902 | B15: INV-415 | C15: Sales | D15: 160 | F15: Hotel Noordeen
A16: 45902 | B16: INV-416 | C16: Sales | D16: 90 | F16: Cash
A17: 45902 | B17: INV-417 | C17: Sales | D17: 3000 | F17: AMEEN MASTER CHEF
A18: 45902 | C18: Water Cane | E18: 160
A19: 45902 | C19: Expences | E19: 100
A20: 45903 | B20: INV-418 | C20: Sales | D20: 1200 | F20: HABIL SAHIB
A21: 45903 | C21: Garlic Purchase | E21: 9825 | G21: Naatu Poondu | H21: 75 | I21: 450 | J21: 125 | K21: SVG Garlics
A22: 45903 | C22: Ginger Purchase | E22: 8000 | G22: Old Ginger | H22: 80 | J22: 100 | K22: Jakakodi Traders
A23: 45903 | B23: INV-419 | C23: Sales | D23: 825 | F23: ARAFATH
A24: 45903 | B24: INV-420 | C24: Sales | D24: 600 | F24: VANJUR SHOP MARKET VASAL
A25: 45903 | B25: INV-421 | C25: Sales | D25: 2040 | F25: Cash
A26: 45903 | B26: INV-422 | C26: Sales | D26: 240 | F26: Hotel Noordeen
A27: 45903 | B27: INV-423 | C27: Sales | D27: 2700 | F27: AL AZEEM CATERS & RESTAURANT
A28: 45903 | B28: INV-424 | C28: Sales | D28: 2250 | F28: HASSIM CATERING | O28: Row Labels | P28: Sum of Sales | Q28: Sum of Expences
A29: 45903 | B29: INV-425 | C29: Sales | D29: 3900 | F29: ARAFATH | O29: Opening Balance | P29: 63725
A30: 45903 | B30: INV-426 | C30: Sales | D30: 5120 | F30: ISMAIL BANDARI (THARANGAPADI ) | O30: Sales | P30: 229785
A31: 45903 | B31: INV-427 | C31: Sales | D31: 360 | F31: HOTEL BISMI | O31: Expences | Q31: 1770
A32: 45903 | C32: Expences | E32: 200 | M32: Maligai Kadai | O32: Packaging Material | Q32: 3378
A33: 45903 | C33: Packaging Material | E33: 638 | M33: Ungal Kadai | O33: Ginger Purchase | Q33: 45609
A34: 45903 | C34: Petrol | E34: 400 | O34: Water Cane | Q34: 760
A35: 45903 | C35: Staff Salary | E35: 300 | M35: Tem Staff | O35: Garlic Purchase | Q35: 81350
A36: 45903 | C36: Trasport | E36: 250 | M36: Auto | O36: Petrol | Q36: 1995
A37: 45903 | C37: Expences | E37: 40 | O37: Staff Salary | Q37: 24400
A38: 45904 | B38: INV-428 | C38: Sales | D38: 5700 | F38: Cash | O38: Trasport | Q38: 1250
A39: 45904 | B39: INV-429 | C39: Sales | D39: 8730 | F39: HASSIM CATERING | O39: Delivery charge | Q39: 450
A40: 45904 | B40: INV-430 | C40: Sales | D40: 1500 | F40: AL AZEEM CATERS & RESTAURANT | O40: Rent | Q40: 9000
A41: 45904 | B41: INV-431 | C41: Sales | D41: 2250 | F41: SAHABUDEEN | O41: Essential Items | Q41: 2253
A42: 45904 | B42: INV-432 | C42: Sales | D42: 1650 | F42: HABEEB | O42: Others | Q42: 820
A43: 45904 | B43: INV-433 | C43: Sales | D43: 320 | F43: Hotel Noordeen | O43: Grand Total | P43: 293510 | Q43: 173035
A44: 45904 | B44: INV-434 | C44: Sales | D44: 600 | F44: BILAL COOK
A45: 45904 | B45: INV-435 | C45: Sales | D45: 540 | F45: HOTEL BISMI
A46: 45904 | B46: INV-436 | C46: Sales | D46: 1500 | F46: DARBAR CATERING
A47: 45904 | B47: INV-437 | C47: Sales | D47: 1040 | F47: Cash
A48: 45904 | B48: INV-438 | C48: Sales | D48: 5250 | F48: AMEEN MASTER CHEF
A49: 45904 | B49: INV-439 | C49: Sales | D49: 3600 | F49: HABIL SAHIB
A50: 45904 | B50: INV-440 | C50: Sales | D50: 600 | F50: RIYAS BANDARI
A51: 45904 | C51: Staff Salary | E51: 400
A52: 45904 | C52: Water Cane | E52: 160 | O52: Row Labels | P52: Sum of Sales
A53: 45904 | C53: Expences | E53: 60 | O53: AL AZEEM CATERS & RESTAURANT | P53: 25200
A54: 45904 | C54: Delivery charge | E54: 200 | O54: AL BAIK MANDI | P54: 2250
A55: 45905 | C55: Ginger Purchase | E55: 3900 | G55: Old Ginger | H55: 78 | J55: 50 | K55: Jakakodi Traders | O55: AMEEN MASTER CHEF | P55: 29430
A56: 45905 | B56: INV-441 | C56: Sales | D56: 640 | F56: Mansoor | O56: Andrew Cook | P56: 1200
A57: 45905 | B57: INV-442 | C57: Sales | D57: 80 | F57: ARAFATH | O57: Ansari | P57: 400
A58: 45905 | B58: INV-443 | C58: Sales | D58: 260 | F58: Cash | O58: AR RAHIM HOTEL | P58: 5500
A59: 45905 | B59: INV-444 | C59: Sales | D59: 320 | F59: YOUSUF BANDARI | O59: ARAFA RESTAURANT | P59: 3040
A60: 45905 | C60: Expences | E60: 50 | O60: ARAFATH | P60: 8115
A61: 45905 | C61: Rent | E61: 9000 | O61: bava chef | P61: 3000
A62: 45905 | B62: INV-445 | C62: Sales | D62: 720 | F62: HOTEL BISMI | O62: BILAL COOK | P62: 9370
A63: 45906 | B63: INV-446 | C63: Sales | D63: 600 | F63: RIYAS BANDARI | O63: Cash | P63: 24750
A64: 45906 | B64: INV-447 | C64: Sales | D64: 1370 | F64: Cash | O64: DARBAR CATERING | P64: 4460
A65: 45906 | B65: INV-448 | C65: Sales | D65: 400 | F65: Hotel Noordeen | O65: HABEEB | P65: 1650
A66: 45906 | B66: INV-449 | C66: Sales | D66: 480 | F66: ARAFA RESTAURANT | O66: HABIL SAHIB | P66: 7580
A67: 45906 | B67: INV-450 | C67: Sales | D67: 2720 | F67: Cash | O67: halidh cook | P67: 11700
A68: 45906 | B68: INV-451 | C68: Sales | D68: 320 | F68: MALAYSIAN FAST FOOD | O68: Hassan | P68: 900
A69: 45906 | B69: INV-452 | C69: Sales | D69: 160 | F69: VANJUR SHOP MARKET VASAL | O69: HASSIM CATERING | P69: 37540
A70: 45906 | B70: INV-453 | C70: Sales | D70: 450 | F70: Cash | O70: HOTEL BISMI | P70: 9960
A71: 45906 | B71: INV-454 | C71: Sales | D71: 2250 | F71: halidh cook | O71: Hotel Noordeen | P71: 6360
A72: 45906 | B72: INV-455 | C72: Sales | D72: 1500 | F72: AL AZEEM CATERS & RESTAURANT | O72: ISMAIL BANDARI (THARANGAPADI ) | P72: 5120
A73: 45906 | B73: INV-456 | C73: Sales | D73: 160 | F73: SANDWICH SHOP | O73: MALAYSIAN FAST FOOD | P73: 1920
A74: 45906 | B74: INV-457 | C74: Sales | D74: 1120 | F74: BILAL COOK | O74: Mansoor | P74: 1840
A75: 45906 | C75: Staff Salary | E75: 300 | M75: Tem Staff | O75: Maraikar Shop | P75: 1200
A76: 45906 | C76: Expences | E76: 50 | O76: Nasar | P76: 100
A77: 45907 | B77: INV-458 | C77: Sales | D77: 750 | F77: AMEEN MASTER CHEF | O77: NFS DELIVERY | P77: 11120
A78: 45907 | B78: INV-459 | C78: Sales | D78: 640 | F78: RR Mini Mart | O78: REAL SUPER MARKET | P78: 400
A79: 45907 | B79: INV-460 | C79: Sales | D79: 240 | F79: Maraikar Shop | O79: RIYAS BANDARI | P79: 2350
A80: 45907 | C80: Expences | E80: 50 | O80: RR Mini Mart | P80: 1760
A81: 45908 | C81: Ginger Purchase | E81: 3900 | G81: Old Ginger | H81: 78 | J81: 50 | K81: Jakakodi Traders | O81: SAHABUDEEN | P81: 2410
A82: 45908 | C82: Garlic Purchase | E82: 9000 | G82: Naatu Poondu | H82: 60 | I82: 600 | J82: 140 | K82: SVG Garlics | O82: SANDWICH SHOP | P82: 820
A83: 45908 | C83: Garlic Purchase | E83: 600 | G83: Desi Udiri | H83: 60 | J83: 10 | K83: SVG Garlics | O83: SUPPLAYKART | P83: 730
A84: 45908 | B84: INV-461 | C84: Sales | D84: 1200 | F84: Mansoor | O84: VANJUR SHOP MARKET VASAL | P84: 1240
A85: 45908 | B85: INV-462 | C85: Sales | D85: 450 | F85: AMEEN MASTER CHEF | O85: YOUSUF BANDARI | P85: 800
A86: 45908 | B86: INV-463 | C86: Sales | D86: 1600 | F86: AR RAHIM HOTEL | O86: (blank) | P86: 63725
A87: 45908 | B87: INV-464 | C87: Sales | D87: 540 | F87: HOTEL BISMI | O87: Burhaan | P87: 160
A88: 45908 | B88: INV-465 | C88: Sales | D88: 240 | F88: Hotel Noordeen | O88: UMAR BRIYANI | P88: 1500
A89: 45908 | B89: INV-466 | C89: Sales | D89: 760 | F89: Cash | O89: AHEE BANDARI | P89: 3750
A90: 45908 | B90: INV-467 | C90: Sales | D90: 300 | F90: ARAFATH | O90: RILWAN | P90: 160
A91: 45908 | B91: INV-468 | C91: Sales | D91: 1500 | F91: AL AZEEM CATERS & RESTAURANT | O91: Grand Total | P91: 293510
A92: 45908 | B92: INV-469 | C92: Sales | D92: 250 | F92: Cash
A93: 45908 | C93: Petrol | E93: 400
A94: 45908 | C94: Staff Salary | E94: 300
A95: 45908 | C95: Expences | E95: 110
A96: 45908 | C96: Delivery charge | E96: 250
A97: 45909 | B97: INV-470 | C97: Sales | D97: 120 | F97: Cash
A98: 45909 | B98: INV-471 | C98: Sales | D98: 450 | F98: AMEEN MASTER CHEF
A99: 45909 | B99: INV-472 | C99: Sales | D99: 980 | F99: HABIL SAHIB
A100: 45909 | B100: INV-473 | C100: Sales | D100: 240 | F100: Hotel Noordeen
...

Sheet Oct 2025 - Sales
A1: Date | B1: Invoice No | C1: Description | D1: Sales | E1: Expences | F1: Bill To | G1: Variety | H1: Unit Price | I1: Transport cost | J1: Qty | K1: Supplier | L1: Credit | M1: Remarks
C2: Opening Balance | D2: 0
A3: 45931 | C3: Ginger Purchase | E3: 3700 | G3: Old Ginger | H3: 74 | J3: 50 | K3: Jakakodi Traders
A4: 45931 | B4: INV-652 | C4: Sales | D4: 510 | F4: NFS Delivery
A5: 45931 | B5: INV-653 | C5: Sales | D5: 240 | F5: Hotel Noordeen
A6: 45931 | B6: INV-654 | C6: Sales | D6: 170 | F6: Cash
A7: 45931 | B7: INV-655 | C7: Sales | D7: 320 | F7: Hotel Bismi
A8: 45931 | B8: INV-656 | C8: Sales | D8: 340 | F8: NFS Delivery
A9: 45931 | B9: INV-657 | C9: Sales | D9: 240 | F9: Maraikar Shop
A10: 45931 | B10: INV-658 | C10: Sales | D10: 320 | F10: Darbar Catering
A11: 45931 | B11: INV-659 | C11: Sales | D11: 750 | F11: Arafath
A12: 45931 | B12: INV-660 | C12: Sales | D12: 320 | F12: NFS Delivery
A13: 45931 | C13: Expences | E13: 50
A14: 45931 | C14: Packaging Material | E14: 80
A15: 45931 | C15: Others | E15: 5400
A16: 45932 | B16: INV-661 | C16: Sales | D16: 510 | F16: NFS Delivery
A17: 45932 | B17: INV-662 | C17: Sales | D17: 480 | F17: Hotel Bismi
A18: 45932 | B18: INV-663 | C18: Sales | D18: 170 | F18: Cash
A19: 45932 | B19: INV-664 | C19: Sales | D19: 320 | F19: Malaysian Fast Food
A20: 45932 | B20: INV-665 | C20: Sales | D20: 3000 | F20: Hassim Catering
A21: 45932 | B21: INV-666 | C21: Sales | D21: 160 | F21: Darbar Catering
A22: 45932 | C22: Expences | E22: 50
A23: 45932 | C23: Delivery charge | E23: 100
A24: 45933 | B24: INV-667 | C24: Sales | D24: 320 | F24: Darbar Catering
A25: 45933 | B25: INV-668 | C25: Sales | D25: 1500 | F25: AL AZEEM CATERS & RESTAURANT
A26: 45933 | B26: INV-669 | C26: Sales | D26: 170 | F26: NFS Delivery
A27: 45933 | B27: INV-670 | C27: Sales | D27: 600 | F27: Halidh Cook
A28: 45933 | B28: INV-671 | C28: Sales | D28: 480 | F28: Hotel Bismi | O28: Row Labels | P28: Sum of Sales | Q28: Sum of Expences
A29: 45933 | B29: INV-672 | C29: Sales | D29: 750 | F29: Ameen Master Chef | O29: Opening Balance | P29: 0
A30: 45933 | B30: INV-673 | C30: Sales | D30: 440 | F30: Hotel Noordeen | O30: Ginger Purchase | Q30: 28820
A31: 45933 | B31: INV-674 | C31: Sales | D31: 600 | F31: Habil Sahib | O31: Sales | P31: 171155 | Q31: 0
A32: 45933 | B32: INV-675 | C32: Sales | D32: 240 | F32: RR mini Mart | O32: Expences | Q32: 1445
A33: 45933 | B33: INV-676 | C33: Sales | D33: 260 | F33: Cash | O33: Packaging Material | Q33: 2350
A34: 45933 | B34: INV-677 | C34: Sales | D34: 2250 | F34: Hassim Catering | O34: Others | Q34: 5900
A35: 45933 | B35: INV-678 | C35: Sales | D35: 510 | F35: NFS Delivery | O35: Delivery charge | Q35: 350
A36: 45933 | C36: Expences | E36: 50 | O36: Staff Salary | Q36: 19650
A37: 45934 | B37: INV-679 | C37: Sales | D37: 480 | F37: Supplaykart | O37: Water Cane | Q37: 480
A38: 45934 | B38: INV-680 | C38: Sales | D38: 770 | F38: Cash | O38: Petrol | Q38: 1980
A39: 45934 | B39: INV-681 | C39: Sales | D39: 1500 | F39: AL AZEEM CATERS & RESTAURANT | O39: Rent | Q39: 9000
A40: 45934 | B40: INV-682 | C40: Sales | D40: 4200 | F40: Ameen Master Chef | O40: Essential Items | Q40: 1687
A41: 45934 | B41: INV-683 | C41: Sales | D41: 640 | F41: Hotel Noordeen | O41: Garlic Purchase | Q41: 42752
A42: 45934 | B42: INV-684 | C42: Sales | D42: 160 | F42: Hassim Catering | O42: Grand Total | P42: 171155 | Q42: 114414
A43: 45934 | B43: INV-685 | C43: Sales | D43: 320 | F43: Andrew Cook
A44: 45934 | B44: INV-686 | C44: Sales | D44: 480 | F44: Hotel Bismi
A45: 45934 | B45: INV-687 | C45: Sales | D45: 300 | F45: Arafath
A46: 45934 | B46: INV-688 | C46: Sales | D46: 460 | F46: Burhaan
A47: 45934 | C47: Staff Salary | E47: 200
A48: 45934 | C48: Water Cane | E48: 160
A49: 45934 | C49: Petrol | E49: 400
A50: 45934 | C50: Expences | E50: 50
A51: 45935 | B51: INV-689 | C51: Sales | D51: 120 | F51: NFS Delivery
A52: 45935 | B52: INV-690 | C52: Sales | D52: 320 | F52: Cash | O52: Row Labels | P52: Sum of Sales | R52: S.No | S52: Customers | T52: Sum of Sales
A53: 45935 | B53: INV-691 | C53: Sales | D53: 240 | F53: Supplaykart | O53: (blank) | P53: 480 | R53: 1 | S53: Hassim Catering | T53: 32300
A54: 45935 | B54: INV-692 | C54: Sales | D54: 3450 | F54: Ya Salaam | O54: NFS Delivery | P54: 12840 | R54: 2 | S54: AL AZEEM CATERS & RESTAURANT | T54: 20700
A55: 45935 | B55: INV-693 | C55: Sales | D55: 1500 | F55: AL AZEEM CATERS & RESTAURANT | O55: Hotel Noordeen | P55: 7880 | R55: 3 | S55: Ameen Master Chef | T55: 17920
A56: 45935 | C56: Rent | E56: 9000 | O56: Cash | P56: 7100 | R56: 4 | S56: NFS Delivery | T56: 12840
A57: 45936 | B57: INV-694 | C57: Sales | D57: 240 | F57: Hotel Noordeen | O57: Hotel Bismi | P57: 9600 | R57: 5 | S57: Hotel Bismi | T57: 9600
A58: 45936 | B58: INV-695 | C58: Sales | D58: 260 | F58: Cash | O58: Maraikar Shop | P58: 1200 | R58: 6 | S58: Halidh Cook | T58: 9180
A59: 45936 | B59: INV-696 | C59: Sales | D59: 320 | F59: Supplaykart | O59: Darbar Catering | P59: 3600 | R59: 7 | S59: Hotel Noordeen | T59: 7880
A60: 45936 | B60: INV-697 | C60: Sales | D60: 320 | F60: Hotel Bismi | O60: Arafath | P60: 2265 | R60: 8 | S60: Cash | T60: 7100
A61: 45936 | B61: INV-698 | C61: Sales | D61: 240 | F61: Maraikar Shop | O61: Malaysian Fast Food | P61: 2240 | R61: 9 | S61: Ar rahim hotel | T61: 5250
A62: 45936 | B62: INV-699 | C62: Sales | D62: 90 | F62: NFS Delivery | O62: Hassim Catering | P62: 32300 | R62: 10 | S62: RILWAN CATERING | T62: 4980
A63: 45936 | B63: INV-700 | C63: Sales | D63: 480 | F63: Darbar Catering | O63: AL AZEEM CATERS & RESTAURANT | P63: 20700 | R63: 11 | S63: ISMAIL BANDARI (THARANGAPADI ) | T63: 4800
A64: 45936 | C64: Ginger Purchase | E64: 5200 | G64: Old Ginger | H64: 104 | J64: 50 | K64: Jakakodi Traders | O64: Halidh Cook | P64: 9180 | R64: 12 | S64: Chennai Tawa Beef | T64: 4480
A65: 45936 | C65: Expences | E65: 56 | O65: Ameen Master Chef | P65: 17920 | R65: 13 | S65: LE ROYAL MANDI | T65: 3750
A66: 45937 | C66: Ginger Purchase | E66: 3300 | G66: Old Ginger | H66: 66 | J66: 50 | K66: Jakakodi Traders | O66: Habil Sahib | P66: 1320 | R66: 14 | S66: Ya Salaam | T66: 3610
A67: 45937 | B67: INV-701 | C67: Sales | D67: 3000 | F67: Hassim Catering | O67: RR mini Mart | P67: 1200 | R67: 15 | S67: Darbar Catering | T67: 3600
A68: 45937 | B68: INV-702 | C68: Sales | D68: 90 | F68: NFS Delivery | O68: Supplaykart | P68: 1880 | R68: 16 | S68: Riyas Bandari | T68: 2700
A69: 45937 | B69: INV-703 | C69: Sales | D69: 270 | F69: Cash | O69: Andrew Cook | P69: 1040 | R69: 17 | S69: Arafath | T69: 2265
A70: 45937 | B70: INV-704 | C70: Sales | D70: 170 | F70: Mansoor | O70: Burhaan | P70: 1180 | R70: 18 | S70: Malaysian Fast Food | T70: 2240
A71: 45937 | B71: INV-705 | C71: Sales | D71: 160 | F71: Hotel Noordeen | O71: Ya Salaam | P71: 3610 | R71: 19 | S71: Supplaykart | T71: 1880
A72: 45937 | B72: INV-706 | C72: Sales | D72: 320 | F72: Darbar Catering | O72: Mansoor | P72: 490 | R72: 20 | S72: Hotel Anas | T72: 1710
A73: 45937 | C73: Expences | E73: 50 | O73: Market Shop | P73: 240 | R73: 21 | S73: Bilal Cook | T73: 1440
A74: 45938 | B74: INV-707 | C74: Sales | D74: 430 | F74: NFS Delivery | O74: AL RAYAAN MANDI | P74: 480 | R74: 22 | S74: Habil Sahib | T74: 1320
A75: 45938 | B75: INV-708 | C75: Sales | D75: 240 | F75: Market Shop | O75: Ar rahim hotel | P75: 5250 | R75: 23 | S75: Maraikar Shop | T75: 1200
A76: 45938 | B76: INV-709 | C76: Sales | D76: 90 | F76: Cash | O76: Faizal Nagai | P76: 300 | R76: 24 | S76: RR mini Mart | T76: 1200
A77: 45938 | B77: INV-710 | C77: Sales | D77: 80 | F77: Hotel Noordeen | O77: VANJUR SHOP MARKET VASAL | P77: 320 | R77: 25 | S77: Burhaan | T77: 1180
A78: 45938 | B78: INV-711 | C78: Sales | D78: 320 | F78: Malaysian Fast Food | O78: Hassan | P78: 700 | R78: 26 | S78: Andrew Cook | T78: 1040
A79: 45938 | B79: INV-712 | C79: Sales | D79: 320 | F79: Hotel Bismi | O79: sandwich shop | P79: 560 | R79: 27 | S79: Hassan | T79: 700
A80: 45938 | B80: INV-713 | C80: Sales | D80: 480 | F80: AL RAYAAN MANDI | O80: habeeb | P80: 340 | R80: 28 | S80: sandwich shop | T80: 560
A81: 45938 | B81: INV-714 | C81: Sales | D81: 1500 | F81: AL AZEEM CATERS & RESTAURANT | O81: ansari | P81: 500 | R81: 29 | S81: ansari | T81: 500
A82: 45938 | C82: Petrol | E82: 380 | O82: Chennai Tawa Beef | P82: 4480 | R82: 30 | S82: Mansoor | T82: 490
A83: 45938 | C83: Expences | E83: 50 | O83: Riyas Bandari | P83: 2700 | R83: 31 | S83: (blank) | T83: 480
A84: 45939 | B84: INV-715 | C84: Sales | D84: 160 | F84: Hotel Noordeen | O84: Bilal Cook | P84: 1440 | R84: 32 | S84: AL RAYAAN MANDI | T84: 480
A85: 45939 | B85: INV-716 | C85: Sales | D85: 480 | F85: Hotel Bismi | O85: Hotel Anas | P85: 1710 | R85: 33 | S85: habeeb | T85: 340
A86: 45939 | B86: INV-717 | C86: Sales | D86: 170 | F86: Cash | O86: ISMAIL BANDARI (THARANGAPADI ) | P86: 4800 | R86: 34 | S86: VANJUR SHOP MARKET VASAL | T86: 320
A87: 45939 | B87: INV-718 | C87: Sales | D87: 160 | F87: Andrew Cook | O87: LE ROYAL MANDI | P87: 3750 | R87: 35 | S87: HOTEL LEBBAI | T87: 320
A88: 45939 | B88: INV-719 | C88: Sales | D88: 3000 | F88: Halidh Cook | O88: HOTEL LEBBAI | P88: 320 | R88: 36 | S88: Faizal Nagai | T88: 300
A89: 45939 | B89: INV-720 | C89: Sales | D89: 750 | F89: Ar rahim hotel | O89: Sahabudeen | P89: 160 | R89: 37 | S89: Market Shop | T89: 240
A90: 45939 | B90: INV-721 | C90: Sales | D90: 450 | F90: Ameen Master Chef | O90: RILWAN CATERING | P90: 4980 | R90: 38 | S90: Sahabudeen | T90: 160
A91: 45939 | B91: INV-722 | C91: Sales | D91: 300 | F91: Faizal Nagai | O91: nasar | P91: 100 | R91: 39 | S91: nasar | T91: 100
A92: 45939 | B92: INV-723 | C92: Sales | D92: 3000 | F92: Hassim Catering | O92: Grand Total | P92: 171155 | S92: Grand Total | T92: 171155
A93: 45939 | C93: Others | E93: 500 | M93: Electrician wage
A94: 45939 | C94: Essential Items | E94: 620 | M94: Hardwares
A95: 45939 | C95: Expences | E95: 50
A96: 45940 | C96: Garlic Purchase | E96: 17431 | G96: Naatu Poondu | H96: 60 | I96: 1051 | J96: 273 | K96: SVG Garlics
A97: 45940 | B97: INV-724 | C97: Sales | D97: 1500 | F97: Hassim Catering
A98: 45940 | B98: INV-725 | C98: Sales | D98: 320 | F98: VANJUR SHOP MARKET VASAL
A99: 45940 | B99: INV-726 | C99: Sales | D99: 160 | F99: Hotel Noordeen
A100: 45940 | B100: INV-727 | C100: Sales | D100: 480 | F100: Hotel Bismi
...

Sheet Nov 2025 - Sales
A1: Date | B1: Invoice No | C1: Description | D1: Sales | E1: Expences | F1: Bill To | G1: Variety | H1: Unit Price | I1: Transport cost | J1: Qty | K1: Supplier | L1: Credit | M1: Remarks
C2: Opening Balance | D2: ='Oct 2025 - Sales'!D353 -> 39169
A3: 45962 | C3: Ginger Purchase | E3: 3300 | G3: Old Ginger | H3: 66 | J3: 50 | K3: Jakakodi Traders
A4: 45962 | B4: INV-923 | C4: Sales | D4: 1350 | F4: AMEEN MASTER CHEF
A5: 45962 | B5: INV-924 | C5: Sales | D5: 240 | F5: HOTEL NOORDEEN
A6: 45962 | B6: INV-925 | C6: Sales | D6: 400 | F6: CHENNAI TAWA BEEF
A7: 45962 | B7: INV-926 | C7: Sales | D7: 160 | F7: FAISAL(NAGAI)
A8: 45962 | B8: INV-927 | C8: Sales | D8: 320 | F8: HOTEL BISMI
A9: 45962 | B9: INV-928 | C9: Sales | D9: 240 | F9: MARAIKAR SHOP
A10: 45962 | B10: INV-929 | C10: Sales | D10: 80 | F10: SUPPLAYKART
A11: 45962 | B11: INV-930 | C11: Sales | D11: 1500 | F11: AL AZEEM CATERS & RESTAURANT
A12: 45962 | B12: INV-931 | C12: Sales | D12: 2250 | F12: HALIDH COOK
A13: 45962 | B13: INV-932 | C13: Sales | D13: 480 | F13: AMEEN MASTER CHEF
A14: 45962 | B14: INV-933 | C14: Sales | D14: 640 | F14: CASH
A15: 45962 | B15: INV-934 | C15: Sales | D15: 320 | F15: HOTEL NOORDEEN
... A18: 45962 | B18: INV-937 | C18: Sales | D18: 1500 | F18: UMAR BRIYANI
A19: 45962 | C19: Staff Salary | E19: 100
A20: 45962 | C20: Expences | E20: 50
A21: 45963 | B21: INV-938 | C21: Sales | D21: 320 | F21: HOTEL BISMI
A22: 45963 | B22: INV-939 | C22: Sales | D22: 1500 | F22: HASSIM CATERING
A23: 45963 | B23: INV-940 | C23: Sales | D23: 1500 | F23: AL AZEEM CATERS & RESTAURANT
A24: 45963 | B24: INV-941 | C24: Sales | D24: 660 | F24: NFS DELIVERY
A25: 45963 | B25: INV-942 | C25: Sales | D25: 480 | F25: CASH
A26: 45964 | B26: INV-943 | C26: Sales | D26: 280 | F26: HOTEL NOORDEEN
A27: 45964 | B27: INV-944 | C27: Sales | D27: 100 | F27: ANSARI
A28: 45964 | B28: INV-945 | C28: Sales | D28: 320 | F28: HOTEL BISMI | O28: Row Labels | P28: Sum of Sales | Q28: Sum of Expences
A29: 45964 | B29: INV-946 | C29: Sales | D29: 1500 | F29: LE ROYAL MANDI | O29: Opening Balance | P29: 39169
A30: 45964 | B30: INV-947 | C30: Sales | D30: 240 | F30: MARAIKAR SHOP | O30: (blank)
A31: 45964 | B31: INV-948 | C31: Sales | D31: 150 | F31: CASH | O31: Ginger Purchase | Q31: 30310.5
A32: 45964 | B32: INV-949 | C32: Sales | D32: 750 | F32: HASSIM CATERING | O32: Sales | P32: 178135
A33: 45964 | C33: Expences | E33: 50 | O33: Staff Salary | Q33: 16770
A34: 45964 | C34: Water Cane | E34: 160 | O34: Expences | Q34: 1240
A35: 45965 | C35: Ginger Purchase | E35: 1810.5 | G35: Old Ginger | H35: 60.35 | J35: 30 | K35: Jakakodi Traders | O35: Water Cane | Q35: 480
A36: 45965 | B36: INV-950 | C36: Sales | D36: 240 | F36: HOTEL NOORDEEN | O36: Rent | Q36: 9000
A37: 45965 | B37: INV-951 | C37: Sales | D37: 320 | F37: CHENNAI TAWA BEEF | O37: Essential Items | Q37: 320
A38: 45965 | B38: INV-952 | C38: Sales | D38: 320 | F38: HOTEL BISMI | O38: Delivery charge | Q38: 758
A39: 45965 | B39: INV-953 | C39: Sales | D39: 90 | F39: NFS DELIVERY | O39: Packaging Material | Q39: 3860
A40: 45965 | B40: INV-954 | C40: Sales | D40: 80 | F40: BURHAAN | O40: Petrol | Q40: 1600
A41: 45965 | B41: INV-955 | C41: Sales | D41: 1500 | F41: HASSIM CATERING | O41: Garlic Purchase | Q41: 51012
A42: 45965 | C42: Staff Salary | E42: 100 | O42: Others | Q42: 480
A43: 45965 | C43: Expences | E43: 50 | O43: Bills | Q43: 900
A44: 45966 | C44: Ginger Purchase | E44: 3100 | G44: Old Ginger | H44: 62 | J44: 50 | K44: Jakakodi Traders | O44: Marketting | Q44: 409
A45: 45966 | B45: INV-956 | C45: Sales | D45: 240 | F45: HOTEL NOORDEEN | O45: Grand Total | P45: 217304 | Q45: 117139.5
A46: 45966 | B46: INV-957 | C46: Sales | D46: 520 | F46: CASH | O46: Gross Revenue | P46: 178135 | Q46: .
A47: 45966 | B47: INV-958 | C47: Sales | D47: 320 | F47: HOTEL BISMI | O47: Total | P47: 217304 | Q47: 117139.5
A48: 45966 | B48: INV-959 | C48: Sales | D48: 240 | F48: CHENNAI TAWA BEEF
A49: 45966 | B49: INV-960 | C49: Sales | D49: 170 | F49: NFS DELIVERY | O49: Net Revenue | P49: 60995.5
A50: 45966 | B50: INV-961 | C50: Sales | D50: 4500 | F50: HASSIM CATERING | O50: Net Balance | P50: 100164.5
A51: 45966 | B51: INV-962 | C51: Sales | D51: 1500 | F51: AL AZEEM CATERS & RESTAURANT | S51: November Sales - Customer wise
A52: 45966 | B52: INV-963 | C52: Sales | D52: 1800 | F52: SAMSU BANDARI | O52: Row Labels | P52: Sum of Sales | S52: Row Labels | T52: Sum of Sales
A53: 45966 | C53: Rent | E53: 9000 | O53: (blank) | P53: 39169
A54: 45966 | C54: Expences | E54: 45 | O54: AMEEN MASTER CHEF | P54: 11305 | S54: HASSIM CATERING | T54: 29300
A55: 45967 | B55: INV-964 | C55: Sales | D55: 240 | F55: CHENNAI TAWA BEEF | O55: HOTEL NOORDEEN | P55: 4520 | S55: AL AZEEM CATERS & RESTAURANT | T55: 25100
A56: 45967 | B56: INV-965 | C56: Sales | D56: 270 | F56: NFS DELIVERY | O56: CHENNAI TAWA BEEF | P56: 7120 | S56: NFS DELIVERY | T56: 14170
A57: 45967 | B57: INV-966 | C57: Sales | D57: 320 | F57: HOTEL BISMI | O57: FAISAL(NAGAI) | P57: 160 | S57: LE ROYAL MANDI | T57: 13580
A58: 45967 | B58: INV-967 | C58: Sales | D58: 80 | F58: BURHAAN | O58: HOTEL BISMI | P58: 8640 | S58: Habil Sahib | T58: 13350
A59: 45967 | B59: INV-968 | C59: Sales | D59: 1500 | F59: HASSIM CATERING | O59: MARAIKAR SHOP | P59: 1520 | S59: AMEEN MASTER CHEF | T59: 11305
A60: 45967 | B60: INV-969 | C60: Sales | D60: 1500 | F60: AL AZEEM CATERS & RESTAURANT | O60: SUPPLAYKART | P60: 1040 | S60: HOTEL BISMI | T60: 8640
A61: 45967 | B61: INV-970 | C61: Sales | D61: 450 | F61: NASAR | O61: AL AZEEM CATERS & RESTAURANT | P61: 25100 | S61: CHENNAI TAWA BEEF | T61: 7120
A62: 45967 | B62: INV-971 | C62: Sales | D62: 90 | F62: CASH | O62: HALIDH COOK | P62: 5350 | S62: RILUWAN(NAGORE) | T62: 6160
A63: 45967 | C63: Expences | E63: 50 | O63: CASH | P63: 3950 | S63: HALIDH COOK | T63: 5350
A64: 45967 | C64: Essential Items | E64: 80 | O64: HOTEL ANAS | P64: 1600 | S64: HOTEL NOORDEEN | T64: 4520
A65: 45968 | B65: INV-972 | C65: Sales | D65: 4500 | F65: HASSIM CATERING | O65: HASSIM CATERING | P65: 29300 | S65: Badhru Idli Kadai | T65: 4050
A66: 45968 | B66: INV-973 | C66: Sales | D66: 260 | F66: NFS DELIVERY | O66: UMAR BRIYANI | P66: 1500 | S66: CASH | T66: 3950
A67: 45968 | B67: INV-974 | C67: Sales | D67: 240 | F67: CHENNAI TAWA BEEF | O67: NFS DELIVERY | P67: 14170 | S67: AR RAHIM HOTEL | T67: 3750
A68: 45968 | B68: INV-975 | C68: Sales | D68: 240 | F68: HOTEL NOORDEEN | O68: ANSARI | P68: 100 | S68: Riyas Bandari | T68: 2570
A69: 45968 | B69: INV-976 | C69: Sales | D69: 480 | F69: HOTEL BISMI | O69: LE ROYAL MANDI | P69: 13580 | S69: ANDREW COOK | T69: 1920
A70: 45968 | B70: INV-977 | C70: Sales | D70: 640 | F70: CASH | O70: BURHAAN | P70: 1120 | S70: SAMSU BANDARI | T70: 1800
A71: 45968 | B71: INV-978 | C71: Sales | D71: 200 | F71: HASSAN | O71: SAMSU BANDARI | P71: 1800 | S71: MALAYSIAN FAST FOOD | T71: 1760
A72: 45968 | B72: INV-979 | C72: Sales | D72: 160 | F72: HOTEL ANAS | O72: NASAR | P72: 450 | S72: HOTEL ANAS | T72: 1600
A73: 45968 | B73: INV-980 | C73: Sales | D73: 750 | F73: AR RAHIM HOTEL | O73: HASSAN | P73: 600 | S73: MARAIKAR SHOP | T73: 1520
A74: 45968 | C74: Expences | E74: 50 | O74: AR RAHIM HOTEL | P74: 3750 | S74: UMAR BRIYANI | T74: 1500
A75: 45969 | B75: INV-981 | C75: Sales | D75: 2250 | F75: AR RAHIM HOTEL | O75: DARBAR CATERING | P75: 1380 | S75: Arafath | T75: 1500
A76: 45969 | B76: INV-982 | C76: Sales | D76: 520 | F76: NFS DELIVERY | O76: ANDREW COOK | P76: 1920 | S76: YA Salaam | T76: 1500
A77: 45969 | B77: INV-983 | C77: Sales | D77: 560 | F77: CHENNAI TAWA BEEF | O77: MALAYSIAN FAST FOOD | P77: 1760 | S77: ARAFA RESTAURANT | T77: 1500
A78: 45969 | B78: INV-984 | C78: Sales | D78: 160 | F78: DARBAR CATERING | O78: RR mini mart | P78: 650 | S78: NOORDIN FOOD COURT | T78: 1440
A79: 45969 | B79: INV-985 | C79: Sales | D79: 320 | F79: HOTEL BISMI | O79: Sandwich shop | P79: 800 | S79: DARBAR CATERING | T79: 1380
A80: 45969 | B80: INV-986 | C80: Sales | D80: 2250 | F80: LE ROYAL MANDI | O80: Yousuf Bandari | P80: 1280 | S80: Yousuf Bandari | T80: 1280
A81: 45969 | B81: INV-987 | C81: Sales | D81: 1500 | F81: AL AZEEM CATERS & RESTAURANT | O81: FAIZAL NAGAI | P81: 640 | S81: BURHAAN | T81: 1120
A82: 45969 | B82: INV-988 | C82: Sales | D82: 240 | F82: MARAIKAR SHOP | O82: Arafath | P82: 1500 | S82: SUPPLAYKART | T82: 1040
A83: 45969 | B83: INV-989 | C83: Sales | D83: 1360 | F83: ANDREW COOK | O83: YA Salaam | P83: 1500 | S83: Sahabudeen | T83: 960
A84: 45969 | B84: INV-990 | C84: Sales | D84: 1500 | F84: HASSIM CATERING | O84: Sahabudeen | P84: 960 | S84: Sandwich shop | T84: 800
A85: 45969 | B85: INV-991 | C85: Sales | D85: 320 | F85: HOTEL NOORDEEN | O85: RILUWAN(NAGORE) | P85: 6160 | S85: RR mini mart | T85: 650
A86: 45969 | B86: INV-992 | C86: Sales | D86: 320 | F86: MALAYSIAN FAST FOOD | O86: Habil Sahib | P86: 13350 | S86: FAIZAL NAGAI | T86: 640
A87: 45969 | C87: Expences | E87: 50 | O87: NOORDIN FOOD COURT | P87: 1440 | S87: HASSAN | T87: 600
A88: 45969 | C88: Staff Salary | E88: 70 | O88: ARAFA RESTAURANT | P88: 1500 | S88: NASAR | T88: 450
A89: 45969 | C89: Delivery charge | E89: 58 | O89: Riyas Bandari | P89: 2570 | S89: FAISAL(NAGAI) | T89: 160
A90: 45969 | C90: Packaging Material | E90: 1050 | O90: Badhru Idli Kadai | P90: 4050 | S90: ANSARI | T90: 100
A91: 45970 | B91: INV-993 | C91: Sales | D91: 340 | F91: CASH | O91: Grand Total | P91: 217304 | S91: Grand Total | T91: =SUM(T54:T90) -> 178135
A92: 45970 | B92: INV-994 | C92: Sales | D92: 870 | F92: NFS DELIVERY
A93: 45971 | C93: Ginger Purchase | E93: 3100 | G93: Old Ginger | H93: 62 | J93: 50 | K93: Jakakodi Traders
A94: 45971 | B94: INV-995 | C94: Sales | D94: 160 | F94: HOTEL NOORDEEN
A95: 45971 | B95: INV-996 | C95: Sales | D95: 320 | F95: HOTEL BISMI
A96: 45971 | B96: INV-997 | C96: Sales | D96: 430 | F96: NFS DELIVERY
A97: 45971 | B97: INV-998 | C97: Sales | D97: 170 | F97: RR mini mart
A98: 45971 | B98: INV-999 | C98: Sales | D98: 240 | F98: CHENNAI TAWA BEEF
A99: 45971 | B99: INV-1000 | C99: sales | D99: 160 | F99: Sandwich shop
A100: 45971 | B100: INV-1001 | C100: Sales | D100: 1500 | F100: AL AZEEM CATERS & RESTAURANT
A101: 45971 | C101: Petrol | E101: 400
A102: 45971 | C102: Essential Items | E102: 45
...

Sheet Dec 2025 - Sales
A1: Date | B1: Invoice No | C1: Description | D1: Sales | E1: Expences | F1: Bill To | G1: Variety | H1: Unit Price | I1: Transport cost | J1: Qty | K1: Supplier | L1: Credit | M1: Remarks
C2: Opening Balance | D2: ='Nov 2025 - Sales'!D321 -> 60995.5
A3: 45992 | B3: INV-1165 | C3: Sales | D3: 1280 | F3: HOTEL BISMI
A4: 45992 | B4: INV-1166 | C4: Sales | D4: 320 | F4: SAHABUDEEN
A5: 45992 | B5: INV-1167 | C5: Sales | D5: 800 | F5: CHENNAI TAWA BEEF
A6: 45992 | B6: INV-1168 | C6: Sales | D6: 160 | F6: NOORDIN FOOD COURT
A7: 45992 | B7: INV-1169 | C7: Sales | D7: 300 | F7: HASSAN
A8: 45992 | B8: INV-1170 | C8: Sales | D8: 2250 | F8: LE ROYAL MANDI
A9: 45992 | B9: INV-1171 | C9: Sales | D9: 90 | F9: Cash
A10: 45992 | B10: INV-1172 | C10: Sales | D10: 170 | F10: NFS DELIVERY
A11: 45992 | B11: INV-1173 | C11: Sales | D11: 160 | F11: BURHAAN
A12: 45992 | B12: INV-1174 | C12: Sales | D12: 640 | F12: HALIDH COOK
A13: 45992 | B13: INV-1175 | C13: Sales | D13: 1500 | F13: HASSIM CATERING
A14: 45992 | C14: Expences | E14: 30 | M14: Bike Repair
A15: 45992 | C15: Water Cane | E15: 160
A16: 45992 | C16: Expences | E16: 50
A17: 45992 | C17: Packaging Material | E17: 430
A18: 45993 | C18: Ginger Purchase | E18: 3400 | G18: Old Ginger | H18: 68 | J18: 50 | K18: Jakakodi Traders
A19: 45993 | C19: Staff Salary | E19: 500 | M19: Saranya Salary advance
A20: 45993 | B20: INV-1176 | C20: Sales | D20: 1500 | F20: ARAFA RESTAURANT
A21: 45993 | B21: INV-1177 | C21: Sales | D21: 260 | F21: Cash
A22: 45993 | B22: INV-1178 | C22: Sales | D22: 240 | F22: NOORDIN FOOD COURT
A23: 45993 | B23: INV-1179 | C23: Sales | D23: 160 | F23: RR MINI MART
A24: 45993 | B24: INV-1180 | C24: Sales | D24: 320 | F24: HOTEL BISMI
A25: 45993 | B25: INV-1181 | C25: Sales | D25: 750 | F25: AR RAHIM HOTEL
A26: 45993 | B26: INV-1182 | C26: Sales | D26: 160 | F26: SUPPLAYKART
A27: 45993 | B27: INV-1183 | C27: Sales | D27: 320 | F27: BURHAAN
A28: 45993 | B28: INV-1184 | C28: Sales | D28: 750 | F28: HASSIM CATERING
A29: 45993 | B29: INV-1185 | C29: Sales | D29: 750 | F29: AMEEN MASTER CHEF | O29: Row Labels | P29: Sum of Sales | Q29: Sum of Expences
A30: 45993 | C30: Expences | E30: 50 | O30: Opening Balance | P30: 60995.5
A31: 45994 | B31: INV-1186 | C31: Sales | D31: 750 | F31: AMEEN MASTER CHEF | O31: (blank)
A32: 45994 | B32: INV-1187 | C32: Sales | D32: 320 | F32: HOTEL BISMI | O32: Sales | P32: 78870
A33: 45994 | B33: INV-1188 | C33: Sales | D33: 320 | F33: MALAYSIAN FAST FOOD | O33: Expences | Q33: 500
A34: 45994 | B34: INV-1189 | C34: Sales | D34: 340 | F34: NFS DELIVERY | O34: Water Cane | Q34: 320
A35: 45994 | B35: INV-1190 | C35: Sales | D35: 1500 | F35: HASSIM CATERING | O35: Packaging Material | Q35: 1020
A36: 45994 | B36: INV-1191 | C36: Sales | D36: 1350 | F36: HABIL SAHIB | O36: Ginger Purchase | Q36: 10300
A37: 45994 | B37: INV-1192 | C37: Sales | D37: 220 | F37: NOORDIN FOOD COURT | O37: Delivery charge | Q37: 600
A38: 45994 | B38: INV-1193 | C38: Sales | D38: 150 | F38: HASSAN | O38: Others | Q38: 8610
A39: 45994 | B39: INV-1194 | C39: Sales | D39: 1600 | F39: AL AZEEM CATERS & RESTAURANT | O39: Rent | Q39: 9000
A40: 45994 | C40: Delivery charge | E40: 50 | O40: Petrol | Q40: 770
A41: 45994 | C41: Others | E41: 30 | O41: Staff Salary | Q41: 5850
A42: 45994 | C42: Expences | E42: 50 | O42: Essential Items | Q42: 60
A43: 45995 | B43: INV-1195 | C43: Sales | D43: 160 | F43: NOORDIN FOOD COURT | O43: Garlic Purchase | Q43: 45300
A44: 45995 | B44: INV-1196 | C44: Sales | D44: 320 | F44: HOTEL BISMI | O44: Grand Total | P44: 139865.5 | Q44: 82330
A45: 45995 | B45: INV-1197 | C45: Sales | D45: 80 | F45: SUPPLAYKART
A46: 45995 | B46: INV-1198 | C46: Sales | D46: 160 | F46: FAIZAL NAGAI
A47: 45995 | B47: INV-1199 | C47: Sales | D47: 340 | F47: CASH
A48: 45995 | B48: INV-1200 | C48: Sales | D48: 160 | F48: HOTEL ANAS
A49: 45995 | B49: INV-1201 | C49: Sales | D49: 3000 | F49: HASSIM CATERING
A50: 45995 | B50: INV-1202 | C50: Sales | D50: 750 | F50: AR RAHIM HOTEL
A51: 45995 | C51: Expences | E51: 50
A52: 45996 | B52: INV-1203 | C52: Sales | D52: 3000 | F52: HASSIM CATERING
A53: 45996 | B53: INV-1204 | C53: Sales | D53: 340 | F53: NFS DELIVERY | O53: Row Labels | P53: Sum of Sales
A54: 45996 | B54: INV-1205 | C54: Sales | D54: 160 | F54: NOORDIN FOOD COURT | O54: (blank) | P54: 60995.5
A55: 45996 | B55: INV-1206 | C55: Sales | D55: 320 | F55: HOTEL BISMI | O55: HOTEL BISMI | P55: 4320
A56: 45996 | B56: INV-1207 | C56: Sales | D56: 80 | F56: FAIZAL NAGAI | O56: SAHABUDEEN | P56: 320
A57: 45996 | B57: INV-1208 | C57: Sales | D57: 3000 | F57: HABEEB | O57: CHENNAI TAWA BEEF | P57: 800
A58: 45996 | B58: INV-1209 | C58: Sales | D58: 750 | F58: AR RAHIM HOTEL | O58: NOORDIN FOOD COURT | P58: 1500
A59: 45996 | B59: INV-1210 | C59: Sales | D59: 510 | F59: NFS DELIVERY | O59: HASSAN | P59: 450
A60: 45996 | B60: INV-1211 | C60: Sales | D60: 1600 | F60: AL AZEEM CATERS & RESTAURANT | O60: LE ROYAL MANDI | P60: 6750
A61: 45996 | C61: Rent | E61: 9000 | O61: Cash | P61: 2070
A62: 45996 | C62: Petrol | E62: 400 | O62: NFS DELIVERY | P62: 12150
A63: 45997 | C63: Staff Salary | E63: 5000 | M63: Saranya Salary advance | O63: BURHAAN | P63: 480
A64: 45997 | C64: Ginger Purchase | E64: 3500 | G64: Old Ginger | H64: 70 | J64: 50 | K64: Jakakodi Traders | O64: HALIDH COOK | P64: 640
A65: 45997 | B65: INV-1212 | C65: Sales | D65: 400 | F65: NOORDIN FOOD COURT | O65: HASSIM CATERING | P65: 15000
A66: 45997 | B66: INV-1213 | C66: Sales | D66: 1500 | F66: AR RAHIM HOTEL | O66: ARAFA RESTAURANT | P66: 2300
A67: 45997 | B67: INV-1214 | C67: Sales | D67: 800 | F67: HOTEL BISMI | O67: RR MINI MART | P67: 160
A68: 45997 | B68: INV-1215 | C68: Sales | D68: 2880 | F68: NFS DELIVERY | O68: AR RAHIM HOTEL | P68: 6750
A69: 45997 | B69: INV-1216 | C69: Sales | D69: 600 | F69: YA SALAAM | O69: SUPPLAYKART | P69: 240
A70: 45997 | B70: INV-1217 | C70: Sales | D70: 720 | F70: Cash | O70: AMEEN MASTER CHEF | P70: 2580
A71: 45997 | B71: INV-1218 | C71: Sales | D71: 480 | F71: AMEEN MASTER CHEF | O71: MALAYSIAN FAST FOOD | P71: 640
A72: 45997 | B72: INV-1219 | C72: Sales | D72: 240 | F72: ANDREW COOK | O72: HABIL SAHIB | P72: 1350
A73: 45997 | C73: Staff Salary | E73: 200 | O73: AL AZEEM CATERS & RESTAURANT | P73: 4800
A74: 45997 | C74: Packaging Material | E74: 160 | O74: FAIZAL NAGAI | P74: 240
A75: 45997 | C75: Expences | E75: 50 | O75: HOTEL ANAS | P75: 320
A76: 45997 | C76: Others | E76: 80 | O76: HABEEB | P76: 6000
A77: 45997 | B77: INV-1220 | C77: Sales | D77: 2000 | F77: RIYAS BANDARI | O77: YA SALAAM | P77: 600
A78: 45997 | B78: INV-1221 | C78: Sales | D78: 1500 | F78: HASSIM CATERING | O78: ANDREW COOK | P78: 240
A79: 45997 | B79: INV-1222 | C79: Sales | D79: 1100 | F79: ANSARI | O79: RIYAS BANDARI | P79: 2000
A80: 45998 | B80: INV-1223 | C80: Sales | D80: 320 | F80: MALAYSIAN FAST FOOD | O80: ANSARI | P80: 1300
A81: 45998 | B81: INV-1224 | C81: Sales | D81: 800 | F81: YOUSUF BANDARI | O81: YOUSUF BANDARI | P81: 800
A82: 45998 | B82: INV-1225 | C82: Sales | D82: 800 | F82: ARAFA RESTAURANT | O82: DARBAR CATERING | P82: 800
A83: 45998 | B83: INV-1226 | C83: Sales | D83: 750 | F83: AR RAHIM HOTEL | O83: ARAFATH | P83: 2850
A84: 45998 | B84: INV-1227 | C84: Sales | D84: 220 | F84: CASH | O84: FAISAL(NAGAI) | P84: 160
A85: 45998 | C85: Expences | E85: 20 | O85: SANDWICH SHOP | P85: 160
A86: 45999 | B86: INV-1228 | C86: Sales | D86: 180 | F86: CASH | O86: NASAR | P86: 100
A87: 45999 | B87: INV-1229 | C87: Sales | D87: 90 | F87: NFS DELIVERY | O87: Grand Total | P87: 139865.5
A88: 45999 | B88: INV-1230 | C88: Sales | D88: 320 | F88: HOTEL BISMI
A89: 45999 | B89: INV-1231 | C89: Sales | D89: 300 | F89: HABEEB
A90: 45999 | B90: INV-1232 | C90: Sales | D90: 750 | F90: HASSIM CATERING
A91: 45999 | B91: INV-1233 | C91: Sales | D91: 480 | F91: DARBAR CATERING
A92: 45999 | C92: Staff Salary | E92: 150
A93: 45999 | C93: Expences | E93: 50
A94: 45999 | C94: Water Cane | E94: 160
A95: 45999 | C95: Packaging Material | E95: 430
A96: 46000 | B96: INV-1234 | C96: Sales | D96: 4500 | F96: LE ROYAL MANDI
A97: 46000 | B97: INV-1235 | C97: Sales | D97: 200 | F97: ANSARI
A98: 46000 | B98: INV-1236 | C98: Sales | D98: 170 | F98: CASH
A99: 46000 | B99: INV-1237 | C99: Sales | D99: 750 | F99: AR RAHIM HOTEL
A100: 46000 | B100: INV-1238 | C100: Sales | D100: 5290 | F100: NFS DELIVERY
...

Sheet P&L - 2025
A3: Profit & Loss - 2025
A5: Month | B5: Sales | C5: Expences | D5: Gross Revenue | E5: Gross Profit | F5: Net Profit
A6: 45689 | B6: ='Feb 2025 - Sales'!C24 -> 21450 | C6: ='Feb 2025 - Sales'!D25 -> 26975 | D6: =B6 -> 21450 | F6: =D6-C6 -> -5525
A7: 45717 | B7: ='Mar 2025 - Sales'!D128 -> 188580 | C7: ='Mar 2025 - Sales'!E129 -> 162135 | D7: =B7 -> 188580 | F7: =D7-C7 -> 26445
A8: 45748 | B8: ='Apr 2025 - Sales'!D104 -> 105060 | C8: ='Apr 2025 - Sales'!E105 -> 114833 | D8: =B8 -> 105060 | F8: =D8-C8 -> -9773
A9: 45778 | B9: ='May 2025 - Sales'!D133 -> 133160 | C9: ='May 2025 - Sales'!E134 -> 154562 | D9: =B9 -> 133160 | F9: =D9-C9 -> -21402
A10: 45809 | B10: ='June 2025 - Sales'!D143 -> 126385 | C10: ='June 2025 - Sales'!E144 -> 173669 | D10: =B10 -> 126385 | F10: =D10-C10 -> -47284
A11: 45839 | B11: ='July 2025 - Sales'!D146 -> 164755 | C11: ='July 2025 - Sales'!E147 -> 89496 | D11: =B11 -> 164755 | F11: =D11-C11 -> 75259
A12: 45870 | B12: ='Aug 2025 - Sales'!D158 -> 173370 | C12: ='Aug 2025 - Sales'!E159 -> 170293 | D12: ='Aug 2025 - Sales'!D158 -> 173370 | F12: =D12-C12 -> 3077
A13: 45901 | B13: ='Sep 2025 - Sales '!D341 -> 229785 | C13: ='Sep 2025 - Sales '!E342 -> 173935 | D13: =B13 -> 229785 | F13: =D13-C13 -> 55850
A14: 45931 | B14: ='Oct 2025 - Sales'!D349 -> 171155 | C14: ='Oct 2025 - Sales'!E350 -> 131986 | D14: =B14 -> 171155 | F14: =D14-C14 -> 39169
A15: 45962 | B15: ='Nov 2025 - Sales'!D318 -> 178135 | C15: ='Nov 2025 - Sales'!E319 -> 117139.5 | D15: =B15 -> 178135 | F15: =D15-C15 -> 60995.5
A16: 45992 | B16: ='Dec 2025 - Sales'!D241 -> 139760 | C16: ='Dec 2025 - Sales'!E242 -> 107266 | D16: =B16 -> 139760 | F16: =D16-C16 -> 32494
A18: Total | B18: =SUM(B6:B17) -> 1631595 | C18: =SUM(C6:C17) -> 1422289.5 | D18: =SUM(D6:D17) -> 1631595 | E18: =SUM(E6:E17) -> 0 | F18: =SUM(F6:F17) -> 209305.5
L19: Row Labels | M19: Sum of Sales | N19: Sum of Expences
L20: 45689 | M20: 21450 | N20: 26975
L21: 45717 | M21: 188580 | N21: 162135
L22: 45748 | M22: 105060 | N22: 114833
A23: Profit Share | L23: 45778 | M23: 133160 | N23: 154562
B24: Nassar | E24: Ansari | H24: Hassan | L24: 45809 | M24: 126385 | N24: 173669
A25: Month | B25: Share | C25: Paid | D25: Balance | E25: Share | F25: Paid | G25: Balance | H25: Share | I25: Paid | J25: Balance | L25: 45839 | M25: 164755 | N25: 89496
A26: 45689 | B26: =(F6/4)*2 -> -2762.5 | C26: 0 | D26: 0 | E26: =(F6/4)*1 -> -1381.25 | F26: 0 | G26: 0 | H26: =(F6/4)*1 -> -1381.25 | I26: 0 | J26: 0 | L26: 45870 | M26: 173370 | N26: 170293
A27: 45717 | B27: =(F7/4)*2 -> 13222.5 | C27: 10460 | D27: =B27-C27 -> 2762.5 | E27: =(F7/4)*1 -> 6611.25 | F27: 5000 | G27: =E27-F27 -> 1611.25 | H27: =(F7/4)*1 -> 6611.25 | I27: 5000 | J27: =H27-I27 -> 1611.25 | L27: 45901 | M27: 229785 | N27: 173935
A28: 45748 | B28: =(F8/4)*2 -> -4886.5 | C28: 0 | D28: 0 | E28: =(F8/4)*1 -> -2443.25 | F28: 0 | G28: 0 | H28: =(F8/4)*1 -> -2443.25 | I28: 0 | J28: 0 | L28: 45931 | M28: 171155 | N28: 131986
A29: 45778 | B29: =(F9/4)*2 -> -10701 | C29: 0 | D29: 0 | E29: =(F9/4)*1 -> -5350.5 | F29: 0 | G29: 0 | H29: =(F9/4)*1 -> -5350.5 | I29: 0 | J29: 0 | L29: 45962 | M29: 178135 | N29: 117139.5
A30: 45809 | B30: =(F10/4)*2 -> -23642 | C30: 0 | D30: 0 | E30: =(F10/4)*1 -> -11821 | F30: 0 | G30: 0 | H30: =(F10/4)*1 -> -11821 | I30: 0 | J30: 0 | L30: 45992 | M30: 139760 | N30: 107266
A31: 45839 | B31: =(F11/4)*2 -> 37629.5 | C31: 0 | D31: 0 | E31: =(F11/4)*1 -> 18814.75 | F31: 0 | G31: 0 | H31: =(F11/4)*1 -> 18814.75 | I31: 0 | J31: 0 | L31: Grand Total | M31: 1631595 | N31: 1422289.5
A32: 45870 | B32: =(F12/4)*2 -> 1538.5 | C32: 0 | D32: 0 | E32: =(F12/4)*1 -> 769.25 | F32: 0 | G32: 0 | H32: =(F12/4)*1 -> 769.25 | I32: 0 | J32: 0
A33: 45901
A34: 45931
A35: 45962
A36: 45992
A38: Total | B38: =SUM(B26:B36) -> 10398.5 | C38: =SUM(C26:C36) -> 10460 | D38: =B38-C38 -> -61.5 | E38: =SUM(E26:E36) -> 5199.25 | F38: =SUM(F26:F36) -> 5000 | G38: =E38-F38 -> 199.25 | H38: =SUM(H26:H36) -> 5199.25 | I38: =SUM(I26:I36) -> 5000 | J38: =H38-I38 -> 199.25
A40: Total Share Paid | B40: =C38+F38+I38 -> 20460

Sheet Sheet2
A1: Advance | B1: Garlic | C1: Jakakodi Traders | D1: ANSARI | E1: Desi 2A
A2: Bills | B2: Ginger | C2: Mass Traders | D2: AHEE BANDARI | E2: Desi 3A
A3: Customer deposit refund | C3: Nilaa Wholesale Supplies | D3: AL AZEEM CATERS & RESTAURANT | E3: Desi 4A
A4: Delivery charge | C4: PK Garlic | D4: AL AZEEM CATERS & RESTAURANT | E4: Desi Bom size
A5: Essential Items | C5: SVG Garlics | D5: AL BAIK MANDI | E5: Desi Udiri
A6: Expences | D6: AL RAYAAN MANDI | E6: Naatu Poondu
A7: Garlic Purchase | D7: AMEEN MASTER CHEF | E7: Old Ginger
A8: Ginger Purchase | D8: ANDREW COOK | E8: Ooty Seed A
A9: Loan | D9: AR RAHIM HOTEL
A10: Machinary Maintenance | D10: ARAFA RESTAURANT
A11: Marketting | D11: ARAFATH
A12: Others | D12: Badhru Idli Kadai
A13: Packaging Material | D13: BARAK VEGETABLES
A14: Petrol | D14: BAVA CHEF
A15: Rent | D15: BILAL COOK
A16: Sales | D16: BURHAAN
A17: Staff Salary | D17: CASH
A18: Trasport | D18: CHENNAI TAWA BEEF
A19: Water Cane | D19: DARBAR CATERING
D20: DIAMOND LODGE
D21: FAISAL(NAGAI)
D22: FAIZAL NAGAI
D23: HABEEB
D24: HABIL SAHIB
D25: HALIDH COOK
D26: HASSAN
D27: HASSIM CATERING
D28: HOTEL ANAS
D29: HOTEL BISMI
D30: HOTEL LEBBAI
D31: HOTEL NOORDEEN
... D61: SADAM BANDARI

Sheet Sheet1
E1: Nila Foods & Spices
A2: Daily Stock & Production
A4: Stock-in | E4: Pre-Production | I4: Post-Production
A5: Date | B5: Material | C5: Weight(Kgs) | E5: Date | F5: Material | G5: Weight(Kgs) | I5: Date | J5: Material | K5: Weight(Kgs)
B6: Ginger / Garlic | F6: Ginger / Garlic | J6: Paste / Peeled

Sheet Sheet3
J5: With Citrix acid
J7: NUTRITIONAL INFORMATION* Per 100g of the Product (Approx) | L7: Nutritional Information per Serving -10g | M7: % Daily Values Per serving (10g)
D9: Month | E9: Ansari's Invoice Balances | G9: Expences | J9: Energy | K9: 99 Kcal | L9: 9.9 Kcal | M9: 0.0043
D10: 45809 | F10: 1300 | J10: Protein | K10: 4.16 g | L10: 0.41 g | M10: ~
D11: 45809 | F11: 2240 | J11: Fiber | K11: 4.95 g | L11: 0.49 g | M11: ~
D12: 45809 | F12: 200 | J12: Carbohydrate | K12: 13.8 g | L12: 1.38 g | M12: ~
D13: 45809 | F13: 600 | J13: Total Sugar | K13: NIL | L13: NIL | M13: 0
D14: 45809 | F14: 960 | J14: Total Fat | K14: 2.97 g | L14: 0.29 g | M14: 0.0013
D15: 45839 | E15: MGK Invoice | F15: 8000 | J15: Trans Fat Not more than | K15: NIL | L15: NIL | M15: ~
E16: FSSAI Expences | G16: 9636 | J16: Cholesterol | K16: NIL | L16: NIL | M16: ~
E17: Machine Belt | G17: 680 | J17: Sodium | K17: 212 mg | L17: 21.2 mg | M17: 0.0139
E18: FSSAI Frame | G18: 100 | J18: Calcium | K18: 11 mg | L18: 1.1 mg | M18: ~
E19: Petrol | G19: 200 | J19: Iron | K19: 0.16 mg | L19: 0.01 mg | M19: ~
E20: Malar Salary Ad | G20: 3000 | J20: *Source: NIN-Nutritive Value of Indian Foods
D21: Total | F21: =SUM(F10:F19) -> 13300 | G21: =SUM(G16:G20) -> 13616 | J21: **Percent Daily Values are based on a 2,000 calorie Diet. Your daily values may be higher or lower depending on your calorie need
D22: Balance | G22: =F21-G21 -> -316
A29: 45839
A30: Date | B30: Invoice No. | C30: Customer | D30: Amount | E30: Payment Status | F30: Balance | G30: Customer
A31: 45839 | B31: INV-236 | C31: ANSARI ( PARTNER ) | D31: 240
A32: 45844 | B32: INV-247 | C32: ANSARI ( PARTNER ) | D32: 480
A33: 45845 | B33: INV-252 | C33: ANSARI ( PARTNER ) | D33: 100 | E33: Paid
A34: 45846 | B34: INV-255 | C34: ANSARI ( PARTNER ) | D34: 100 | E34: Paid
A35: 45848 | B35: INV-260 | C35: ANSARI ( PARTNER ) | D35: 240
A36: 45849 | B36: INV-265 | C36: ANSARI ( PARTNER ) | D36: 8160 | E36: Paid | G36: 8000 Paid MGK
A37: 45857 | B37: INV-286 | C37: ANSARI ( PARTNER ) | D37: 4500 | E37: Paid | F37: 4950 | G37: Bava Mandi
A38: 45861 | B38: INV-300 | C38: ANSARI ( PARTNER ) | D38: 200 | E38: Paid
A39: 45866 | B39: INV-311 | C39: ANSARI ( PARTNER ) | D39: 6000 | E39: Paid | F39: 5700 | G39: Peerodam St, 300 Auto
C40: Total | D40: =SUM(D31:D39) -> 20020 | I40: 19500
I41: 8240
A42: 45870
A43: Date | B43: Invoice No | C43: Customer | D43: Amount | E43: Payment Status | G43: Customer
A44: 45870 | B44: INV-324 | C44: ANSARI ( PARTNER ) | D44: 100 | E44: Paid
A45: 45872 | B45: INV-331 | C45: ANSARI ( PARTNER ) | D45: 2100 | E45: 1700 Paid | F45: 400 | G45: RS 1700 Paid Nagai delivery
A46: 45876 | B46: INV-343 | C46: ANSARI ( PARTNER ) | D46: 5400 | E46: 3000 Paid | F46: 2400 | G46: 16kg Rs 2400 Shaha Malim Rs 3000 M Palli | J46: 3000
A47: 45878 | B47: INV-348 | C47: ANSARI ( PARTNER ) | D47: 13500 | F47: 13500 | G47: 90 Shaha Malim | J47: 900
A48: 45879 | B48: INV-350 | C48: ANSARI ( PARTNER ) | D48: 3600 | F48: 3600 | G48: 24 Saha Malim | J48: 1700
A49: 45882 | B49: INV-359 | C49: ANSARI ( PARTNER ) | E49: 900 Paid | F49: 460 | G49: 6kg Sulaiman 900 Paid 4kg Nagai 460 Unpaid | J49: 5700
C50: Total | D50: =SUM(D44:D48) -> 24700 | J50: 4950 | K50: Paid
C52: Jul & Aug Total | D52: =SUM(D50,D40) -> 44720
I55: 37690 | J55: 19500
J56: 5000
J57: 4950
J58: =SUM(J55:J57) -> 29450
I59: =I55-J58 -> 8240

Sheet DashBoard
A4: Sales Dashboard

Sheet Sheet5
A2: August | D2: July
A3: Values | D3: Values
A4: Count of Invoice No | B4: 88 | D4: Count of Invoice No | E4: 90
A5: Sum of Sales | B5: 234018 | D5: Sum of Sales | E5: 150144
A6: Sum of Expences | B6: 170293 | D6: Sum of Expences | E6: 89496
